{"search_result_name": "Cournillens", "language": "it", "id": "000995", "version": "2005-08-16", "_text": "Cournillens\n\nEx com. FR, distr. Lac, dal 1997 unito al com. di Misery-Courtion; (1000/31: Corlingino; 1228 Curlinin; antico nome ted.: Kurlin). Villaggio francofono situato sulla frontiera linguistica e caratterizzato da insediamento sparso dell'abitato. Pop: 234 ab. nel 1811, 251 nel 1850, 321 nel 1900, 328 nel 1930, 309 nel 1950, 264 nel 1990. Un castello \u00e8 menz. nel 1393. Nel 1228 Rodolfo di Neuch\u00e2tel infeud\u00f2 a quattro patrizi friburghesi la decima di C., che divenne progressivamente propriet\u00e0 di Friburgo. Numerose fondazioni e acquisizioni appartenevano al convento di Hauterive e all'H\u00f4pital des Bourgeois. I Bernesi incendiarono C. durante la guerra di Laupen (1339). Fino al 1798 il com. fece parte delle Anciennes Terres (\"bandiera\" dell'H\u00f4pital), del distr. di Avenches fino al 1803, poi di quello di Friburgo fino al 1848. Dalla met\u00e0 del XV sec. ca. \u00e8 attestata la dipendenza del com. dalla parrocchia di Courtion. La cappella di S. Leodegario corrisponde probabilmente al santuario che Rodolfo III di Borgogna cedette nel 1000/1031 al convento di Saint-Maurice; restaurata e completata con un eremo nel 1466, divenne meta di pellegrinaggio. Dal 1495 esiste un regolamento com., dove dal 1645 si menz. la presenza di un balivo (gouverneur). Tra il 1848 e il 1988 nella localit\u00e0 aveva sede la corte di giustizia e pace del primo circ. del distr. del Lac. Nel 1862 si procedette ai lavori di bonifica delle paludi. L'economia del villaggio \u00e8 caratterizzata dall'allevamento, dalla foraggicoltura e dalle cerealicolture.", "scraper_version": "0.2.0", "tags": [{"tag": "Entit\u00e0 politiche / Ex comune", "url": "/it/search/category?f_hls.lexicofacet_string=2/006800.006900.007200."}], "title": "Cournillens", "authors_translators": ["Autrice/Autore:\nMarianne Rolle\nTraduzione:\nPaola Crivelli"], "text_links": [[{"start": 0, "end": 11, "mention": null, "origin": "entity_fishing", "annotation": {"wikidata_entity_id": "Q1137689", "wikipedia_page_id": 7810529, "wikipedia_page_title": null, "wikidata_entity_url": "http://www.wikidata.org/entity/Q1137689", "grobid_tag": null, "extra_fields": {"rawName": "allevamento", "confidence_score": 0.4019, "domains": ["Agriculture"], "origin": "entity_fishing"}}, "href": "it/articles/000995", "dhsid": "000995", "wiki": {"item": "http://www.wikidata.org/entity/Q1137689", "itemLabel": "Cournillens", "dhsid": "000995", "namefr": "Cournillens", "articlefr": "https://fr.wikipedia.org/wiki/Cournillens", "namede": "Cournillens", "articlede": "https://de.wikipedia.org/wiki/Cournillens", "nameit": "Cournillens", "articleit": "https://it.wikipedia.org/wiki/Cournillens", "nameen": "", "articleen": "", "instanceof": "http://www.wikidata.org/entity/Q685309", "instanceofLabel": "ancienne commune de Suisse", "gndid": "7749683-8", "wikidata_id": "Q1137689"}}], [{"start": 8, "end": 10, "mention": null, "origin": "entity_fishing", "annotation": {"wikidata_entity_id": "Q16181", "wikipedia_page_id": 3532, "wikipedia_page_title": null, "wikidata_entity_url": "http://www.wikidata.org/entity/Q16181", "grobid_tag": null, "extra_fields": {"rawName": "allevamento", "confidence_score": 0.4019, "domains": ["Agriculture"], "origin": "entity_fishing"}}}, {"start": 50, "end": 65, "mention": null, "origin": "entity_fishing", "annotation": {"wikidata_entity_id": "Q67326", "wikipedia_page_id": 245111, "wikipedia_page_title": null, "wikidata_entity_url": "http://www.wikidata.org/entity/Q67326", "grobid_tag": null, "extra_fields": {"rawName": "allevamento", "confidence_score": 0.4019, "domains": ["Agriculture"], "origin": "entity_fishing"}}, "href": "it/articles/045856", "dhsid": "045856", "wiki": {"item": "http://www.wikidata.org/entity/Q67326", "itemLabel": "Misery-Courtion", "dhsid": "045856", "namefr": "Misery-Courtion", "articlefr": "https://fr.wikipedia.org/wiki/Misery-Courtion", "namede": "Misery-Courtion", "articlede": "https://de.wikipedia.org/wiki/Misery-Courtion", "nameit": "Misery-Courtion", "articleit": "https://it.wikipedia.org/wiki/Misery-Courtion", "nameen": "Misery-Courtion", "articleen": "https://en.wikipedia.org/wiki/Misery-Courtion", "instanceof": "http://www.wikidata.org/entity/Q70208", "instanceofLabel": "commune de Suisse", "gndid": "7749680-2", "wikidata_id": "Q67326"}}, {"start": 221, "end": 227, "mention": null, "origin": "entity_fishing", "annotation": {"wikidata_entity_id": "Q954172", "wikipedia_page_id": 1887461, "wikipedia_page_title": null, "wikidata_entity_url": "http://www.wikidata.org/entity/Q954172", "grobid_tag": null, "extra_fields": {"rawName": "allevamento", "confidence_score": 0.4019, "domains": ["Agriculture"], "origin": "entity_fishing"}}}, {"start": 385, "end": 394, "mention": null, "origin": "entity_fishing", "annotation": {"wikidata_entity_id": "Q69345", "wikipedia_page_id": 291579, "wikipedia_page_title": null, "wikidata_entity_url": "http://www.wikidata.org/entity/Q69345", "grobid_tag": null, "extra_fields": {"rawName": "allevamento", "confidence_score": 0.4019, "domains": ["Agriculture"], "origin": "entity_fishing"}}, "href": "it/articles/002853", "dhsid": "002853", "wiki": {"item": "http://www.wikidata.org/entity/Q69345", "itemLabel": "Neuch\u00e2tel", "dhsid": "002853", "namefr": "Neuch\u00e2tel", "articlefr": "https://fr.wikipedia.org/wiki/Neuch%C3%A2tel", "namede": "Neuenburg NE", "articlede": "https://de.wikipedia.org/wiki/Neuenburg_NE", "nameit": "Neuch\u00e2tel", "articleit": "https://it.wikipedia.org/wiki/Neuch%C3%A2tel", "nameen": "Neuch\u00e2tel", "articleen": "https://en.wikipedia.org/wiki/Neuch%C3%A2tel", "instanceof": "http://www.wikidata.org/entity/Q5119", "instanceofLabel": "capitale", "gndid": "4075303-7", "wikidata_id": "Q69345"}}, {"start": 446, "end": 448, "mention": null, "origin": "entity_fishing", "annotation": {"wikidata_entity_id": "Q1137689", "wikipedia_page_id": 7810529, "wikipedia_page_title": null, "wikidata_entity_url": "http://www.wikidata.org/entity/Q1137689", "grobid_tag": null, "extra_fields": {"rawName": "allevamento", "confidence_score": 0.4019, "domains": ["Agriculture"], "origin": "entity_fishing"}}, "href": "it/articles/000995", "dhsid": "000995", "wiki": {"item": "http://www.wikidata.org/entity/Q1137689", "itemLabel": "Cournillens", "dhsid": "000995", "namefr": "Cournillens", "articlefr": "https://fr.wikipedia.org/wiki/Cournillens", "namede": "Cournillens", "articlede": "https://de.wikipedia.org/wiki/Cournillens", "nameit": "Cournillens", "articleit": "https://it.wikipedia.org/wiki/Cournillens", "nameen": "", "articleen": "", "instanceof": "http://www.wikidata.org/entity/Q685309", "instanceofLabel": "ancienne commune de Suisse", "gndid": "7749683-8", "wikidata_id": "Q1137689"}}, {"start": 554, "end": 575, "mention": null, "origin": "entity_fishing", "annotation": {"wikidata_entity_id": "Q444740", "wikipedia_page_id": 2478873, "wikipedia_page_title": null, "wikidata_entity_url": "http://www.wikidata.org/entity/Q444740", "grobid_tag": null, "extra_fields": {"rawName": "allevamento", "confidence_score": 0.4019, "domains": ["Agriculture"], "origin": "entity_fishing"}}, "href": "it/articles/012142", "dhsid": "012142", "wiki": {"item": "http://www.wikidata.org/entity/Q444740", "itemLabel": "abbaye d'Hauterive", "dhsid": "012142", "namefr": "Abbaye d'Hauterive", "articlefr": "https://fr.wikipedia.org/wiki/Abbaye_d%27Hauterive", "namede": "Kloster Hauterive", "articlede": "https://de.wikipedia.org/wiki/Kloster_Hauterive", "nameit": "Abbazia di Hauterive", "articleit": "https://it.wikipedia.org/wiki/Abbazia_di_Hauterive", "nameen": "Hauterive Abbey", "articleen": "https://en.wikipedia.org/wiki/Hauterive_Abbey", "instanceof": "http://www.wikidata.org/entity/Q160742", "instanceofLabel": "abbaye", "gndid": "4374810-7", "wikidata_id": "Q444740"}}, {"start": 628, "end": 630, "mention": null, "origin": "entity_fishing", "annotation": {"wikidata_entity_id": "Q1137689", "wikipedia_page_id": 7810529, "wikipedia_page_title": null, "wikidata_entity_url": "http://www.wikidata.org/entity/Q1137689", "grobid_tag": null, "extra_fields": {"rawName": "allevamento", "confidence_score": 0.4019, "domains": ["Agriculture"], "origin": "entity_fishing"}}, "href": "it/articles/000995", "dhsid": "000995", "wiki": {"item": "http://www.wikidata.org/entity/Q1137689", "itemLabel": "Cournillens", "dhsid": "000995", "namefr": "Cournillens", "articlefr": "https://fr.wikipedia.org/wiki/Cournillens", "namede": "Cournillens", "articlede": "https://de.wikipedia.org/wiki/Cournillens", "nameit": "Cournillens", "articleit": "https://it.wikipedia.org/wiki/Cournillens", "nameen": "", "articleen": "", "instanceof": "http://www.wikidata.org/entity/Q685309", "instanceofLabel": "ancienne commune de Suisse", "gndid": "7749683-8", "wikidata_id": "Q1137689"}}, {"start": 652, "end": 658, "mention": null, "origin": "entity_fishing", "annotation": {"wikidata_entity_id": "Q67112", "wikipedia_page_id": 360382, "wikipedia_page_title": null, "wikidata_entity_url": "http://www.wikidata.org/entity/Q67112", "grobid_tag": null, "extra_fields": {"rawName": "allevamento", "confidence_score": 0.4019, "domains": ["Agriculture"], "origin": "entity_fishing"}}, "href": "it/articles/008447", "dhsid": "008447", "wiki": {"item": "http://www.wikidata.org/entity/Q67112", "itemLabel": "Laupen", "dhsid": "008447", "namefr": "Laupen", "articlefr": "https://fr.wikipedia.org/wiki/Laupen", "namede": "Laupen", "articlede": "https://de.wikipedia.org/wiki/Laupen", "nameit": "Laupen", "articleit": "https://it.wikipedia.org/wiki/Laupen", "nameen": "Laupen", "articleen": "https://en.wikipedia.org/wiki/Laupen", "instanceof": "http://www.wikidata.org/entity/Q70208", "instanceofLabel": "commune de Suisse", "gndid": "4099094-1", "wikidata_id": "Q67112"}}, {"start": 763, "end": 771, "mention": null, "origin": "entity_fishing", "annotation": {"wikidata_entity_id": "Q43236", "wikipedia_page_id": 359645, "wikipedia_page_title": null, "wikidata_entity_url": "http://www.wikidata.org/entity/Q43236", "grobid_tag": null, "extra_fields": {"rawName": "allevamento", "confidence_score": 0.4019, "domains": ["Agriculture"], "origin": "entity_fishing"}}, "href": "it/articles/002308", "dhsid": "002308", "wiki": {"item": "http://www.wikidata.org/entity/Q43236", "itemLabel": "Avenches", "dhsid": "002308", "namefr": "Avenches", "articlefr": "https://fr.wikipedia.org/wiki/Avenches", "namede": "Avenches", "articlede": "https://de.wikipedia.org/wiki/Avenches", "nameit": "Avenches", "articleit": "https://it.wikipedia.org/wiki/Avenches", "nameen": "Avenches", "articleen": "https://en.wikipedia.org/wiki/Avenches", "instanceof": "http://www.wikidata.org/entity/Q70208", "instanceofLabel": "commune de Suisse", "gndid": "4004007-0", "wikidata_id": "Q43236"}}, {"start": 841, "end": 847, "mention": null, "origin": "entity_fishing", "annotation": {"wikidata_entity_id": "Q7018", "wikipedia_page_id": 10107, "wikipedia_page_title": null, "wikidata_entity_url": "http://www.wikidata.org/entity/Q7018", "grobid_tag": null, "extra_fields": {"rawName": "allevamento", "confidence_score": 0.4019, "domains": ["Agriculture"], "origin": "entity_fishing"}}}, {"start": 894, "end": 904, "mention": null, "origin": "entity_fishing", "annotation": {"wikidata_entity_id": "Q102496", "wikipedia_page_id": 2125503, "wikipedia_page_title": null, "wikidata_entity_url": "http://www.wikidata.org/entity/Q102496", "grobid_tag": null, "extra_fields": {"rawName": "allevamento", "confidence_score": 0.4019, "domains": ["Agriculture"], "origin": "entity_fishing"}}, "href": "it/articles/011744", "dhsid": "011744", "wiki": {"item": "http://www.wikidata.org/entity/Q102496", "itemLabel": "paroisse eccl\u00e9siastique", "dhsid": "011744", "namefr": "Paroisse", "articlefr": "https://fr.wikipedia.org/wiki/Paroisse", "namede": "Pfarrei", "articlede": "https://de.wikipedia.org/wiki/Pfarrei", "nameit": "Parrocchia", "articleit": "https://it.wikipedia.org/wiki/Parrocchia", "nameen": "Parish", "articleen": "https://en.wikipedia.org/wiki/Parish", "instanceof": "http://www.wikidata.org/entity/Q15617994", "instanceofLabel": "type de division administrative", "gndid": "4115544-0", "wikidata_id": "Q102496"}}, {"start": 908, "end": 916, "mention": null, "origin": "entity_fishing", "annotation": {"wikidata_entity_id": "Q15803959", "wikipedia_page_id": 245119, "wikipedia_page_title": null, "wikidata_entity_url": "http://www.wikidata.org/entity/Q15803959", "grobid_tag": null, "extra_fields": {"rawName": "allevamento", "confidence_score": 0.4019, "domains": ["Agriculture"], "origin": "entity_fishing"}}, "href": "it/articles/000998", "dhsid": "000998", "wiki": {"item": "http://www.wikidata.org/entity/Q15803959", "itemLabel": "Courtion", "dhsid": "000998", "namefr": "Courtion", "articlefr": "https://fr.wikipedia.org/wiki/Courtion", "namede": "Courtion", "articlede": "https://de.wikipedia.org/wiki/Courtion", "nameit": "Courtion", "articleit": "https://it.wikipedia.org/wiki/Courtion", "nameen": "", "articleen": "", "instanceof": "http://www.wikidata.org/entity/Q70208", "instanceofLabel": "commune de Suisse", "gndid": "7749685-1", "wikidata_id": "Q15803959"}}, {"start": 990, "end": 1013, "mention": null, "origin": "entity_fishing", "annotation": {"wikidata_entity_id": "Q504792", "wikipedia_page_id": 745864, "wikipedia_page_title": null, "wikidata_entity_url": "http://www.wikidata.org/entity/Q504792", "grobid_tag": null, "extra_fields": {"rawName": "allevamento", "confidence_score": 0.4019, "domains": ["Agriculture"], "origin": "entity_fishing"}}, "href": "it/articles/020780", "dhsid": "020780", "wiki": {"item": "http://www.wikidata.org/entity/Q504792", "itemLabel": "Rodolphe III de Bourgogne", "dhsid": "020780", "namefr": "Rodolphe III de Bourgogne", "articlefr": "https://fr.wikipedia.org/wiki/Rodolphe_III_de_Bourgogne", "namede": "Rudolf III. (Burgund)", "articlede": "https://de.wikipedia.org/wiki/Rudolf_III._(Burgund)", "nameit": "Rodolfo III di Borgogna", "articleit": "https://it.wikipedia.org/wiki/Rodolfo_III_di_Borgogna", "nameen": "Rudolph III of Burgundy", "articleen": "https://en.wikipedia.org/wiki/Rudolph_III_of_Burgundy", "instanceof": "http://www.wikidata.org/entity/Q5", "instanceofLabel": "\u00eatre humain", "gndid": "104254998", "wikidata_id": "Q504792"}}, {"start": 1051, "end": 1064, "mention": null, "origin": "entity_fishing", "annotation": {"wikidata_entity_id": "Q69545", "wikipedia_page_id": 370020, "wikipedia_page_title": null, "wikidata_entity_url": "http://www.wikidata.org/entity/Q69545", "grobid_tag": null, "extra_fields": {"rawName": "allevamento", "confidence_score": 0.4019, "domains": ["Agriculture"], "origin": "entity_fishing"}}, "href": "it/articles/002774", "dhsid": "002774", "wiki": {"item": "http://www.wikidata.org/entity/Q69545", "itemLabel": "Saint-Maurice", "dhsid": "002774", "namefr": "Saint-Maurice (Valais)", "articlefr": "https://fr.wikipedia.org/wiki/Saint-Maurice_(Valais)", "namede": "Saint-Maurice VS", "articlede": "https://de.wikipedia.org/wiki/Saint-Maurice_VS", "nameit": "Saint-Maurice (Svizzera)", "articleit": "https://it.wikipedia.org/wiki/Saint-Maurice_(Svizzera)", "nameen": "Saint-Maurice, Switzerland", "articleen": "https://en.wikipedia.org/wiki/Saint-Maurice,_Switzerland", "instanceof": "http://www.wikidata.org/entity/Q70208", "instanceofLabel": "commune de Suisse", "gndid": "4118257-1", "wikidata_id": "Q69545"}}, {"start": 1129, "end": 1143, "mention": null, "origin": "entity_fishing", "annotation": {"wikidata_entity_id": "Q1644573", "wikipedia_page_id": 116964, "wikipedia_page_title": null, "wikidata_entity_url": "http://www.wikidata.org/entity/Q1644573", "grobid_tag": null, "extra_fields": {"rawName": "allevamento", "confidence_score": 0.4019, "domains": ["Agriculture"], "origin": "entity_fishing"}}}, {"start": 1223, "end": 1229, "mention": null, "origin": "entity_fishing", "annotation": {"wikidata_entity_id": "Q10970991", "wikipedia_page_id": 645489, "wikipedia_page_title": null, "wikidata_entity_url": "http://www.wikidata.org/entity/Q10970991", "grobid_tag": null, "extra_fields": {"rawName": "allevamento", "confidence_score": 0.4019, "domains": ["Agriculture"], "origin": "entity_fishing"}}}, {"start": 1304, "end": 1320, "mention": null, "origin": "entity_fishing", "annotation": {"wikidata_entity_id": "Q588013", "wikipedia_page_id": 2313444, "wikipedia_page_title": null, "wikidata_entity_url": "http://www.wikidata.org/entity/Q588013", "grobid_tag": null, "extra_fields": {"rawName": "allevamento", "confidence_score": 0.4019, "domains": ["Agriculture"], "origin": "entity_fishing"}}}, {"start": 1408, "end": 1414, "mention": null, "origin": "entity_fishing", "annotation": {"wikidata_entity_id": "Q166735", "wikipedia_page_id": 2420656, "wikipedia_page_title": null, "wikidata_entity_url": "http://www.wikidata.org/entity/Q166735", "grobid_tag": null, "extra_fields": {"rawName": "allevamento", "confidence_score": 0.4019, "domains": ["Agriculture"], "origin": "entity_fishing"}}}, {"start": 1418, "end": 1426, "mention": null, "origin": "entity_fishing", "annotation": {"wikidata_entity_id": "Q159810", "wikipedia_page_id": 701085, "wikipedia_page_title": null, "wikidata_entity_url": "http://www.wikidata.org/entity/Q159810", "grobid_tag": null, "extra_fields": {"rawName": "allevamento", "confidence_score": 0.4019, "domains": ["Agriculture"], "origin": "entity_fishing"}}}, {"start": 1463, "end": 1474, "mention": null, "origin": "entity_fishing", "annotation": {"wikidata_entity_id": "Q80962", "wikipedia_page_id": 27112, "wikipedia_page_title": null, "wikidata_entity_url": "http://www.wikidata.org/entity/Q80962", "grobid_tag": null, "extra_fields": {"rawName": "allevamento", "confidence_score": 0.4019, "domains": ["Agriculture"], "origin": "entity_fishing"}}}]], "sources": {"Studi": [{"text": "MAS FR, 4, 1989, 113-132", "tpub": ["MAS FR"], "link": ["https://ekds.ch/library/book:081"]}]}, "metagrid_id": null, "metagrid_links": [], "notice_links": [{"title": "GND", "url": "http://d-nb.info/gnd/7749683-8"}], "bref": [], "text_blocks": [["h1", "Cournillens"], ["p", "Ex com. FR, distr. Lac, dal 1997 unito al com. di Misery-Courtion; (1000/31: Corlingino; 1228 Curlinin; antico nome ted.: Kurlin). Villaggio francofono situato sulla frontiera linguistica e caratterizzato da insediamento sparso dell'abitato. Pop: 234 ab. nel 1811, 251 nel 1850, 321 nel 1900, 328 nel 1930, 309 nel 1950, 264 nel 1990. Un castello \u00e8 menz. nel 1393. Nel 1228 Rodolfo di Neuch\u00e2tel infeud\u00f2 a quattro patrizi friburghesi la decima di C., che divenne progressivamente propriet\u00e0 di Friburgo. Numerose fondazioni e acquisizioni appartenevano al convento di Hauterive e all'H\u00f4pital des Bourgeois. I Bernesi incendiarono C. durante la guerra di Laupen (1339). Fino al 1798 il com. fece parte delle Anciennes Terres (\"bandiera\" dell'H\u00f4pital), del distr. di Avenches fino al 1803, poi di quello di Friburgo fino al 1848. Dalla met\u00e0 del XV sec. ca. \u00e8 attestata la dipendenza del com. dalla parrocchia di Courtion. La cappella di S. Leodegario corrisponde probabilmente al santuario che Rodolfo III di Borgogna cedette nel 1000/1031 al convento di Saint-Maurice; restaurata e completata con un eremo nel 1466, divenne meta di pellegrinaggio. Dal 1495 esiste un regolamento com., dove dal 1645 si menz. la presenza di un balivo (gouverneur). Tra il 1848 e il 1988 nella localit\u00e0 aveva sede la corte di giustizia e pace del primo circ. del distr. del Lac. Nel 1862 si procedette ai lavori di bonifica delle paludi. L'economia del villaggio \u00e8 caratterizzata dall'allevamento, dalla foraggicoltura e dalle cerealicolture."]], "wiki_links": [{"item": "http://www.wikidata.org/entity/Q1137689", "itemLabel": "Cournillens", "dhsid": "000995", "namefr": "Cournillens", "articlefr": "https://fr.wikipedia.org/wiki/Cournillens", "namede": "Cournillens", "articlede": "https://de.wikipedia.org/wiki/Cournillens", "nameit": "Cournillens", "articleit": "https://it.wikipedia.org/wiki/Cournillens", "nameen": "", "articleen": "", "instanceof": "http://www.wikidata.org/entity/Q70208", "instanceofLabel": "commune de Suisse", "gndid": "7749683-8"}, {"item": "http://www.wikidata.org/entity/Q1137689", "itemLabel": "Cournillens", "dhsid": "000995", "namefr": "Cournillens", "articlefr": "https://fr.wikipedia.org/wiki/Cournillens", "namede": "Cournillens", "articlede": "https://de.wikipedia.org/wiki/Cournillens", "nameit": "Cournillens", "articleit": "https://it.wikipedia.org/wiki/Cournillens", "nameen": "", "articleen": "", "instanceof": "http://www.wikidata.org/entity/Q685309", "instanceofLabel": "ancienne commune de Suisse", "gndid": "7749683-8"}], "wikidata_url": "http://www.wikidata.org/entity/Q1137689", "wikipedia_page_title": "Cournillens", "added_wikidata_wikipedia_to_text_links": true, "_initial": "C", "url": "https://hls-dhs-dss.ch/it/articles/000995/2005-08-16"}