{"search_result_name": "Rotten, Elisabeth Friederike", "language": "it", "id": "009375", "version": "2010-11-16", "_text": "Elisabeth Friederike Rotten\n\n15.2.1882 Berlino, 2.5.1964 Londra, rif., di Fischenthal. Figlia di Markus, ingegnere, e di Luisa Peter. Nubile. Cresciuta a Berlino in una fam. cosmopolita, studi\u00f2 germanistica, filosofia e lingue moderne in diverse univ. ted., conseguendo il dottorato nel 1912. Durante la prima guerra mondiale si dedic\u00f2 all'aiuto dei prigionieri di guerra e al pacifismo e nel 1914 fu cofondatrice del Centro di consulenza e di aiuto per cittadini ted. all'estero e stranieri in Germania. Dopo la guerra prosegu\u00ec il suo lavoro di pacificazione nel campo della pedagogia e lavor\u00f2 a livello intern. con figure di spicco del movimento pacifista e della riforma pedagogica. Nel 1921 diede vita, insieme ad Adolphe Ferri\u00e8re e Beatrice Ensor, all'Unione mondiale per il rinnovamento dell'educazione, di cui fu membro del comitato fondatore e, dal 1949, vicepres. Fino al 1933 prese parte a diversi tentativi di riforma pedagogica in Germania. Dal 1934 visse a Saanen. Nel 1944 partecip\u00f2 alla realizzazione del villaggio Pestalozzi a Trogen. Dopo la seconda guerra mondiale a livello politico R. rivendic\u00f2 in particolare il disarmo e il controllo intern. degli armamenti e tenne conferenze in tutta Europa. Fu autrice di numerose opere di carattere pacifista e pedagogico, lavor\u00f2 per diverse riviste specializzate e dal 1922 al 1932 fu curatrice della rivista di educazione da lei fondata Das werdende Zeitalter. Cofondatrice dell'Ufficio intern. dell'educazione a Ginevra (1925), dal 1919 fece parte dell'ufficio presidenziale della Lega ted. per la SdN (direzione del settore dell'educazione). Fu inoltre vicepres. dell'Ass. Montessori intern. (1937) e cofondatrice della Federazione intern. delle comunit\u00e0 di bambini (1948).", "scraper_version": "0.2.0", "tags": [{"tag": "Formazione e scienze / Scuola e formazione", "url": "/it/search/category?f_hls.lexicofacet_string=2/000100.135600.135700."}, {"tag": "Formazione e scienze / Scienze / Pedagogia", "url": "/it/search/category?f_hls.lexicofacet_string=3/000100.135600.136000.137400."}, {"tag": "Movimenti sociali / Pacifismo", "url": "/it/search/category?f_hls.lexicofacet_string=2/000100.144400.145200."}], "title": "Elisabeth Friederike Rotten", "given_name": "Elisabeth Friederike", "family_name": "Rotten", "authors_translators": ["Autrice/Autore:\nRegula Ludi\nTraduzione:\nStefania Ortelli"], "text_links": [[], [{"start": 10, "end": 17, "mention": null, "origin": "entity_fishing", "annotation": {"wikidata_entity_id": "Q64", "wikipedia_page_id": 808, "wikipedia_page_title": null, "wikidata_entity_url": "http://www.wikidata.org/entity/Q64", "grobid_tag": null, "extra_fields": {"rawName": "Montessori", "confidence_score": 0.3689, "domains": ["Pedagogy"], "origin": "entity_fishing"}}, "href": "it/articles/006583", "dhsid": "006583", "wiki": {"item": "http://www.wikidata.org/entity/Q64", "itemLabel": "Berlin", "dhsid": "006583", "namefr": "Berlin", "articlefr": "https://fr.wikipedia.org/wiki/Berlin", "namede": "Berlin", "articlede": "https://de.wikipedia.org/wiki/Berlin", "nameit": "Berlino", "articleit": "https://it.wikipedia.org/wiki/Berlino", "nameen": "Berlin", "articleen": "https://en.wikipedia.org/wiki/Berlin", "instanceof": "http://www.wikidata.org/entity/Q5119", "instanceofLabel": "capitale", "gndid": "4005728-8", "wikidata_id": "Q64"}}, {"start": 28, "end": 34, "mention": null, "origin": "entity_fishing", "annotation": {"wikidata_entity_id": "Q84", "wikipedia_page_id": 2279266, "wikipedia_page_title": null, "wikidata_entity_url": "http://www.wikidata.org/entity/Q84", "grobid_tag": null, "extra_fields": {"rawName": "Montessori", "confidence_score": 0.3689, "domains": ["Pedagogy"], "origin": "entity_fishing"}}, "href": "it/articles/006594", "dhsid": "006594", "wiki": {"item": "http://www.wikidata.org/entity/Q84", "itemLabel": "Londres", "dhsid": "006594", "namefr": "Londres", "articlefr": "https://fr.wikipedia.org/wiki/Londres", "namede": "London", "articlede": "https://de.wikipedia.org/wiki/London", "nameit": "Londra", "articleit": "https://it.wikipedia.org/wiki/Londra", "nameen": "London", "articleen": "https://en.wikipedia.org/wiki/London", "instanceof": "http://www.wikidata.org/entity/Q717478", "instanceofLabel": "subdivision du Royaume-Uni", "gndid": "4074335-4", "wikidata_id": "Q84"}}, {"start": 36, "end": 39, "mention": null, "origin": "entity_fishing", "annotation": {"wikidata_entity_id": "Q275491", "wikipedia_page_id": 595044, "wikipedia_page_title": null, "wikidata_entity_url": "http://www.wikidata.org/entity/Q275491", "grobid_tag": null, "extra_fields": {"rawName": "Montessori", "confidence_score": 0.3689, "domains": ["Pedagogy"], "origin": "entity_fishing"}}}, {"start": 45, "end": 56, "mention": null, "origin": "entity_fishing", "annotation": {"wikidata_entity_id": "Q65854", "wikipedia_page_id": 127926, "wikipedia_page_title": null, "wikidata_entity_url": "http://www.wikidata.org/entity/Q65854", "grobid_tag": null, "extra_fields": {"rawName": "Montessori", "confidence_score": 0.3689, "domains": ["Pedagogy"], "origin": "entity_fishing"}}, "href": "it/articles/000086", "dhsid": "000086", "wiki": {"item": "http://www.wikidata.org/entity/Q65854", "itemLabel": "Fischenthal", "dhsid": "000086", "namefr": "Fischenthal", "articlefr": "https://fr.wikipedia.org/wiki/Fischenthal", "namede": "Fischenthal", "articlede": "https://de.wikipedia.org/wiki/Fischenthal", "nameit": "Fischenthal", "articleit": "https://it.wikipedia.org/wiki/Fischenthal", "nameen": "Fischenthal", "articleen": "https://en.wikipedia.org/wiki/Fischenthal", "instanceof": "http://www.wikidata.org/entity/Q70208", "instanceofLabel": "commune de Suisse", "gndid": "4690505-4", "wikidata_id": "Q65854"}}, {"start": 123, "end": 132, "mention": null, "origin": "entity_fishing", "annotation": {"wikidata_entity_id": "Q708426", "wikipedia_page_id": 77599, "wikipedia_page_title": null, "wikidata_entity_url": "http://www.wikidata.org/entity/Q708426", "grobid_tag": null, "extra_fields": {"rawName": "Montessori", "confidence_score": 0.3689, "domains": ["Pedagogy"], "origin": "entity_fishing"}}}, {"start": 145, "end": 156, "mention": null, "origin": "entity_fishing", "annotation": {"wikidata_entity_id": "Q188843", "wikipedia_page_id": 734960, "wikipedia_page_title": null, "wikidata_entity_url": "http://www.wikidata.org/entity/Q188843", "grobid_tag": null, "extra_fields": {"rawName": "Montessori", "confidence_score": 0.3689, "domains": ["Pedagogy"], "origin": "entity_fishing"}}}, {"start": 165, "end": 177, "mention": null, "origin": "entity_fishing", "annotation": {"wikidata_entity_id": "Q166153", "wikipedia_page_id": 1971861, "wikipedia_page_title": null, "wikidata_entity_url": "http://www.wikidata.org/entity/Q166153", "grobid_tag": null, "extra_fields": {"rawName": "Montessori", "confidence_score": 0.3689, "domains": ["Pedagogy"], "origin": "entity_fishing"}}}, {"start": 179, "end": 188, "mention": null, "origin": "entity_fishing", "annotation": {"wikidata_entity_id": "Q5891", "wikipedia_page_id": 1876512, "wikipedia_page_title": null, "wikidata_entity_url": "http://www.wikidata.org/entity/Q5891", "grobid_tag": null, "extra_fields": {"rawName": "Montessori", "confidence_score": 0.3689, "domains": ["Pedagogy"], "origin": "entity_fishing"}}}, {"start": 244, "end": 253, "mention": null, "origin": "entity_fishing", "annotation": {"wikidata_entity_id": "Q752297", "wikipedia_page_id": 135482, "wikipedia_page_title": null, "wikidata_entity_url": "http://www.wikidata.org/entity/Q752297", "grobid_tag": null, "extra_fields": {"rawName": "Montessori", "confidence_score": 0.3689, "domains": ["Pedagogy"], "origin": "entity_fishing"}}}, {"start": 321, "end": 342, "mention": null, "origin": "entity_fishing", "annotation": {"wikidata_entity_id": "Q179637", "wikipedia_page_id": 533766, "wikipedia_page_title": null, "wikidata_entity_url": "http://www.wikidata.org/entity/Q179637", "grobid_tag": null, "extra_fields": {"rawName": "Montessori", "confidence_score": 0.3689, "domains": ["Pedagogy"], "origin": "entity_fishing"}}}, {"start": 348, "end": 357, "mention": null, "origin": "entity_fishing", "annotation": {"wikidata_entity_id": "Q58848", "wikipedia_page_id": 98605, "wikipedia_page_title": null, "wikidata_entity_url": "http://www.wikidata.org/entity/Q58848", "grobid_tag": null, "extra_fields": {"rawName": "Montessori", "confidence_score": 0.3689, "domains": ["Pedagogy"], "origin": "entity_fishing"}}, "href": "it/articles/027157", "dhsid": "027157", "wiki": {"item": "http://www.wikidata.org/entity/Q58848", "itemLabel": "pacifisme", "dhsid": "027157", "namefr": "Pacifisme", "articlefr": "https://fr.wikipedia.org/wiki/Pacifisme", "namede": "Pazifismus", "articlede": "https://de.wikipedia.org/wiki/Pazifismus", "nameit": "Pacifismo", "articleit": "https://it.wikipedia.org/wiki/Pacifismo", "nameen": "Pacifism", "articleen": "https://en.wikipedia.org/wiki/Pacifism", "instanceof": "http://www.wikidata.org/entity/Q12909644", "instanceofLabel": "id\u00e9ologie politique", "gndid": "4075961-1", "wikidata_id": "Q58848"}}, {"start": 466, "end": 474, "mention": null, "origin": "entity_fishing", "annotation": {"wikidata_entity_id": "Q183", "wikipedia_page_id": 2381197, "wikipedia_page_title": null, "wikidata_entity_url": "http://www.wikidata.org/entity/Q183", "grobid_tag": null, "extra_fields": {"rawName": "Montessori", "confidence_score": 0.3689, "domains": ["Pedagogy"], "origin": "entity_fishing"}}, "href": "it/articles/003352", "dhsid": "003352", "wiki": {"item": "http://www.wikidata.org/entity/Q183", "itemLabel": "Allemagne", "dhsid": "003352", "namefr": "Allemagne", "articlefr": "https://fr.wikipedia.org/wiki/Allemagne", "namede": "Deutschland", "articlede": "https://de.wikipedia.org/wiki/Deutschland", "nameit": "Germania", "articleit": "https://it.wikipedia.org/wiki/Germania", "nameen": "Germany", "articleen": "https://en.wikipedia.org/wiki/Germany", "instanceof": "http://www.wikidata.org/entity/Q7270", "instanceofLabel": "r\u00e9publique", "gndid": "4011882-4", "wikidata_id": "Q183"}}, {"start": 547, "end": 556, "mention": null, "origin": "entity_fishing", "annotation": {"wikidata_entity_id": "Q7922", "wikipedia_page_id": 62057, "wikipedia_page_title": null, "wikidata_entity_url": "http://www.wikidata.org/entity/Q7922", "grobid_tag": null, "extra_fields": {"rawName": "Montessori", "confidence_score": 0.3689, "domains": ["Pedagogy"], "origin": "entity_fishing"}}, "href": "it/articles/008281", "dhsid": "008281", "wiki": {"item": "http://www.wikidata.org/entity/Q7922", "itemLabel": "p\u00e9dagogie", "dhsid": "008281", "namefr": "P\u00e9dagogie", "articlefr": "https://fr.wikipedia.org/wiki/P%C3%A9dagogie", "namede": "P\u00e4dagogik", "articlede": "https://de.wikipedia.org/wiki/P%C3%A4dagogik", "nameit": "Pedagogia", "articleit": "https://it.wikipedia.org/wiki/Pedagogia", "nameen": "Pedagogy", "articleen": "https://en.wikipedia.org/wiki/Pedagogy", "instanceof": "http://www.wikidata.org/entity/Q2465832", "instanceofLabel": "discipline scientifique", "gndid": "4044302-4", "wikidata_id": "Q7922"}}, {"start": 609, "end": 628, "mention": null, "origin": "entity_fishing", "annotation": {"wikidata_entity_id": "Q708312", "wikipedia_page_id": 67371, "wikipedia_page_title": null, "wikidata_entity_url": "http://www.wikidata.org/entity/Q708312", "grobid_tag": null, "extra_fields": {"rawName": "Montessori", "confidence_score": 0.3689, "domains": ["Pedagogy"], "origin": "entity_fishing"}}}, {"start": 689, "end": 705, "mention": null, "origin": "entity_fishing", "annotation": {"wikidata_entity_id": "Q2484549", "wikipedia_page_id": 3649021, "wikipedia_page_title": null, "wikidata_entity_url": "http://www.wikidata.org/entity/Q2484549", "grobid_tag": null, "extra_fields": {"rawName": "Montessori", "confidence_score": 0.3689, "domains": ["Pedagogy"], "origin": "entity_fishing"}}, "href": "it/articles/009020", "dhsid": "009020", "wiki": {"item": "http://www.wikidata.org/entity/Q2484549", "itemLabel": "Adolphe Ferri\u00e8re", "dhsid": "009020", "namefr": "Adolphe Ferri\u00e8re", "articlefr": "https://fr.wikipedia.org/wiki/Adolphe_Ferri%C3%A8re", "namede": "Adolphe Ferri\u00e8re", "articlede": "https://de.wikipedia.org/wiki/Adolphe_Ferri%C3%A8re", "nameit": "Adolphe Ferri\u00e8re", "articleit": "https://it.wikipedia.org/wiki/Adolphe_Ferri%C3%A8re", "nameen": "Adolphe Ferri\u00e8re", "articleen": "https://en.wikipedia.org/wiki/Adolphe_Ferri%C3%A8re", "instanceof": "http://www.wikidata.org/entity/Q5", "instanceofLabel": "\u00eatre humain", "gndid": "124031412", "wikidata_id": "Q2484549"}}, {"start": 717, "end": 722, "mention": null, "origin": "entity_fishing", "annotation": {"wikidata_entity_id": "Q158840", "wikipedia_page_id": 117971, "wikipedia_page_title": null, "wikidata_entity_url": "http://www.wikidata.org/entity/Q158840", "grobid_tag": null, "extra_fields": {"rawName": "Montessori", "confidence_score": 0.3689, "domains": ["Pedagogy"], "origin": "entity_fishing"}}}, {"start": 914, "end": 922, "mention": null, "origin": "entity_fishing", "annotation": {"wikidata_entity_id": "Q183", "wikipedia_page_id": 2381197, "wikipedia_page_title": null, "wikidata_entity_url": "http://www.wikidata.org/entity/Q183", "grobid_tag": null, "extra_fields": {"rawName": "Montessori", "confidence_score": 0.3689, "domains": ["Pedagogy"], "origin": "entity_fishing"}}, "href": "it/articles/003352", "dhsid": "003352", "wiki": {"item": "http://www.wikidata.org/entity/Q183", "itemLabel": "Allemagne", "dhsid": "003352", "namefr": "Allemagne", "articlefr": "https://fr.wikipedia.org/wiki/Allemagne", "namede": "Deutschland", "articlede": "https://de.wikipedia.org/wiki/Deutschland", "nameit": "Germania", "articleit": "https://it.wikipedia.org/wiki/Germania", "nameen": "Germany", "articleen": "https://en.wikipedia.org/wiki/Germany", "instanceof": "http://www.wikidata.org/entity/Q7270", "instanceofLabel": "r\u00e9publique", "gndid": "4011882-4", "wikidata_id": "Q183"}}, {"start": 1001, "end": 1011, "mention": null, "origin": "entity_fishing", "annotation": {"wikidata_entity_id": "Q105428", "wikipedia_page_id": 231197, "wikipedia_page_title": null, "wikidata_entity_url": "http://www.wikidata.org/entity/Q105428", "grobid_tag": null, "extra_fields": {"rawName": "Montessori", "confidence_score": 0.3689, "domains": ["Pedagogy"], "origin": "entity_fishing"}}, "href": "it/articles/009054", "dhsid": "009054", "wiki": {"item": "http://www.wikidata.org/entity/Q105428", "itemLabel": "Johann Heinrich Pestalozzi", "dhsid": "009054", "namefr": "Johann Heinrich Pestalozzi", "articlefr": "https://fr.wikipedia.org/wiki/Johann_Heinrich_Pestalozzi", "namede": "Johann Heinrich Pestalozzi", "articlede": "https://de.wikipedia.org/wiki/Johann_Heinrich_Pestalozzi", "nameit": "Johann Heinrich Pestalozzi", "articleit": "https://it.wikipedia.org/wiki/Johann_Heinrich_Pestalozzi", "nameen": "Johann Heinrich Pestalozzi", "articleen": "https://en.wikipedia.org/wiki/Johann_Heinrich_Pestalozzi", "instanceof": "http://www.wikidata.org/entity/Q5", "instanceofLabel": "\u00eatre humain", "gndid": "118592912", "wikidata_id": "Q105428"}}, {"start": 1014, "end": 1020, "mention": null, "origin": "entity_fishing", "annotation": {"wikidata_entity_id": "Q68189", "wikipedia_page_id": 123749, "wikipedia_page_title": null, "wikidata_entity_url": "http://www.wikidata.org/entity/Q68189", "grobid_tag": null, "extra_fields": {"rawName": "Montessori", "confidence_score": 0.3689, "domains": ["Pedagogy"], "origin": "entity_fishing"}}, "href": "it/articles/001304", "dhsid": "001304", "wiki": {"item": "http://www.wikidata.org/entity/Q68189", "itemLabel": "Trogen", "dhsid": "001304", "namefr": "Trogen", "articlefr": "https://fr.wikipedia.org/wiki/Trogen", "namede": "Trogen AR", "articlede": "https://de.wikipedia.org/wiki/Trogen_AR", "nameit": "Trogen (Svizzera)", "articleit": "https://it.wikipedia.org/wiki/Trogen_(Svizzera)", "nameen": "Trogen, Switzerland", "articleen": "https://en.wikipedia.org/wiki/Trogen,_Switzerland", "instanceof": "http://www.wikidata.org/entity/Q70208", "instanceofLabel": "commune de Suisse", "gndid": "4106969-9", "wikidata_id": "Q68189"}}, {"start": 1030, "end": 1053, "mention": null, "origin": "entity_fishing", "annotation": {"wikidata_entity_id": "Q362", "wikipedia_page_id": 3862, "wikipedia_page_title": null, "wikidata_entity_url": "http://www.wikidata.org/entity/Q362", "grobid_tag": null, "extra_fields": {"rawName": "Montessori", "confidence_score": 0.3689, "domains": ["Pedagogy"], "origin": "entity_fishing"}}, "href": "it/articles/008927", "dhsid": "008927", "wiki": {"item": "http://www.wikidata.org/entity/Q362", "itemLabel": "Seconde Guerre mondiale", "dhsid": "008927", "namefr": "Seconde Guerre mondiale", "articlefr": "https://fr.wikipedia.org/wiki/Seconde_Guerre_mondiale", "namede": "Zweiter Weltkrieg", "articlede": "https://de.wikipedia.org/wiki/Zweiter_Weltkrieg", "nameit": "Seconda guerra mondiale", "articleit": "https://it.wikipedia.org/wiki/Seconda_guerra_mondiale", "nameen": "World War II", "articleen": "https://en.wikipedia.org/wiki/World_War_II", "instanceof": "http://www.wikidata.org/entity/Q103495", "instanceofLabel": "guerre mondiale", "gndid": "4079167-1", "wikidata_id": "Q362"}}, {"start": 1179, "end": 1185, "mention": null, "origin": "entity_fishing", "annotation": {"wikidata_entity_id": "Q46", "wikipedia_page_id": 650233, "wikipedia_page_title": null, "wikidata_entity_url": "http://www.wikidata.org/entity/Q46", "grobid_tag": null, "extra_fields": {"rawName": "Montessori", "confidence_score": 0.3689, "domains": ["Pedagogy"], "origin": "entity_fishing"}}, "href": "it/articles/007147", "dhsid": "007147", "wiki": {"item": "http://www.wikidata.org/entity/Q46", "itemLabel": "Europe", "dhsid": "007147", "namefr": "Europe", "articlefr": "https://fr.wikipedia.org/wiki/Europe", "namede": "Europa", "articlede": "https://de.wikipedia.org/wiki/Europa", "nameit": "Europa", "articleit": "https://it.wikipedia.org/wiki/Europa", "nameen": "Europe", "articleen": "https://en.wikipedia.org/wiki/Europe", "instanceof": "http://www.wikidata.org/entity/Q2418896", "instanceofLabel": "zone continentale et \u00eeles environnantes", "gndid": "4015701-5", "wikidata_id": "Q46"}}, {"start": 1229, "end": 1238, "mention": null, "origin": "entity_fishing", "annotation": {"wikidata_entity_id": "Q58848", "wikipedia_page_id": 98605, "wikipedia_page_title": null, "wikidata_entity_url": "http://www.wikidata.org/entity/Q58848", "grobid_tag": null, "extra_fields": {"rawName": "Montessori", "confidence_score": 0.3689, "domains": ["Pedagogy"], "origin": "entity_fishing"}}, "href": "it/articles/027157", "dhsid": "027157", "wiki": {"item": "http://www.wikidata.org/entity/Q58848", "itemLabel": "pacifisme", "dhsid": "027157", "namefr": "Pacifisme", "articlefr": "https://fr.wikipedia.org/wiki/Pacifisme", "namede": "Pazifismus", "articlede": "https://de.wikipedia.org/wiki/Pazifismus", "nameit": "Pacifismo", "articleit": "https://it.wikipedia.org/wiki/Pacifismo", "nameen": "Pacifism", "articleen": "https://en.wikipedia.org/wiki/Pacifism", "instanceof": "http://www.wikidata.org/entity/Q12909644", "instanceofLabel": "id\u00e9ologie politique", "gndid": "4075961-1", "wikidata_id": "Q58848"}}, {"start": 1445, "end": 1452, "mention": null, "origin": "entity_fishing", "annotation": {"wikidata_entity_id": "Q71", "wikipedia_page_id": 1895856, "wikipedia_page_title": null, "wikidata_entity_url": "http://www.wikidata.org/entity/Q71", "grobid_tag": null, "extra_fields": {"rawName": "Montessori", "confidence_score": 0.3689, "domains": ["Pedagogy"], "origin": "entity_fishing"}}, "href": "it/articles/002903", "dhsid": "002903", "wiki": {"item": "http://www.wikidata.org/entity/Q71", "itemLabel": "Gen\u00e8ve", "dhsid": "002903", "namefr": "Gen\u00e8ve", "articlefr": "https://fr.wikipedia.org/wiki/Gen%C3%A8ve", "namede": "Genf", "articlede": "https://de.wikipedia.org/wiki/Genf", "nameit": "Ginevra", "articleit": "https://it.wikipedia.org/wiki/Ginevra", "nameen": "Geneva", "articleen": "https://en.wikipedia.org/wiki/Geneva", "instanceof": "http://www.wikidata.org/entity/Q1549591", "instanceofLabel": "grande ville", "gndid": "4020137-5", "wikidata_id": "Q71"}}, {"start": 1531, "end": 1534, "mention": null, "origin": "entity_fishing", "annotation": {"wikidata_entity_id": "Q38130", "wikipedia_page_id": 11641, "wikipedia_page_title": null, "wikidata_entity_url": "http://www.wikidata.org/entity/Q38130", "grobid_tag": null, "extra_fields": {"rawName": "Montessori", "confidence_score": 0.3689, "domains": ["Pedagogy"], "origin": "entity_fishing"}}, "href": "it/articles/026468", "dhsid": "026468", "wiki": {"item": "http://www.wikidata.org/entity/Q38130", "itemLabel": "Soci\u00e9t\u00e9 des Nations", "dhsid": "026468", "namefr": "Soci\u00e9t\u00e9 des Nations", "articlefr": "https://fr.wikipedia.org/wiki/Soci%C3%A9t%C3%A9_des_Nations", "namede": "V\u00f6lkerbund", "articlede": "https://de.wikipedia.org/wiki/V%C3%B6lkerbund", "nameit": "Societ\u00e0 delle Nazioni", "articleit": "https://it.wikipedia.org/wiki/Societ%C3%A0_delle_Nazioni", "nameen": "League of Nations", "articleen": "https://en.wikipedia.org/wiki/League_of_Nations", "instanceof": "http://www.wikidata.org/entity/Q245065", "instanceofLabel": "organisation intergouvernementale", "gndid": "36500-2", "wikidata_id": "Q38130"}}, {"start": 1607, "end": 1617, "mention": null, "origin": "entity_fishing", "annotation": {"wikidata_entity_id": "Q131117", "wikipedia_page_id": 710579, "wikipedia_page_title": null, "wikidata_entity_url": "http://www.wikidata.org/entity/Q131117", "grobid_tag": null, "extra_fields": {"rawName": "Montessori", "confidence_score": 0.3689, "domains": ["Pedagogy"], "origin": "entity_fishing"}}}]], "sources": {"Studi": [{"text": "Schweizer Biographisches Archiv, 4, 1954, 112 sg. (con elenco delle op.)", "tpub": ["Schweizer Biographisches Archiv"]}, {"text": "Neue Wege, 58, 1964, 134 sg., 210-212", "tpub": ["Neue Wege"]}, {"text": "Der neue Bund, 30, 1964, n. 3 (n. speciale)", "tpub": ["Der neue Bund"]}, {"text": "D. Haubfleisch, \u00abE. Rotten (1882-1964)\u00bb, in \"Etwas erz\u00e4hlen\", a cura di I. Hansen-Schaberg, 1997, 114-131", "author": ["D. Haubfleisch"], "tpub": ["E. Rotten (1882-1964)", "\"Etwas erz\u00e4hlen\""]}]}, "metagrid_id": "9375", "metagrid_links": [{}], "notice_links": [{"title": "GND", "url": "http://d-nb.info/gnd/124382088"}, {"title": "VIAF", "url": "http://viaf.org/viaf/22493063"}], "bref": [{"title": "Dati biografici", "text": "\u2217\ufe0e 15.2.1882\n   \u271d\ufe0e 2.5.1964\n1882-02-151964-05-02", "birth_date": "1882-02-15", "death_date": "1964-05-02"}], "birth_date": "1882-02-15", "death_date": "1964-05-02", "text_blocks": [["h1", "Elisabeth Friederike Rotten"], ["p", "15.2.1882 Berlino, 2.5.1964 Londra, rif., di Fischenthal. Figlia di Markus, ingegnere, e di Luisa Peter. Nubile. Cresciuta a Berlino in una fam. cosmopolita, studi\u00f2 germanistica, filosofia e lingue moderne in diverse univ. ted., conseguendo il dottorato nel 1912. Durante la prima guerra mondiale si dedic\u00f2 all'aiuto dei prigionieri di guerra e al pacifismo e nel 1914 fu cofondatrice del Centro di consulenza e di aiuto per cittadini ted. all'estero e stranieri in Germania. Dopo la guerra prosegu\u00ec il suo lavoro di pacificazione nel campo della pedagogia e lavor\u00f2 a livello intern. con figure di spicco del movimento pacifista e della riforma pedagogica. Nel 1921 diede vita, insieme ad Adolphe Ferri\u00e8re e Beatrice Ensor, all'Unione mondiale per il rinnovamento dell'educazione, di cui fu membro del comitato fondatore e, dal 1949, vicepres. Fino al 1933 prese parte a diversi tentativi di riforma pedagogica in Germania. Dal 1934 visse a Saanen. Nel 1944 partecip\u00f2 alla realizzazione del villaggio Pestalozzi a Trogen. Dopo la seconda guerra mondiale a livello politico R. rivendic\u00f2 in particolare il disarmo e il controllo intern. degli armamenti e tenne conferenze in tutta Europa. Fu autrice di numerose opere di carattere pacifista e pedagogico, lavor\u00f2 per diverse riviste specializzate e dal 1922 al 1932 fu curatrice della rivista di educazione da lei fondata Das werdende Zeitalter. Cofondatrice dell'Ufficio intern. dell'educazione a Ginevra (1925), dal 1919 fece parte dell'ufficio presidenziale della Lega ted. per la SdN (direzione del settore dell'educazione). Fu inoltre vicepres. dell'Ass. Montessori intern. (1937) e cofondatrice della Federazione intern. delle comunit\u00e0 di bambini (1948)."]], "wiki_links": [{"item": "http://www.wikidata.org/entity/Q96597", "itemLabel": "Elisabeth Rotten", "dhsid": "009375", "namefr": "Elisabeth Rotten", "articlefr": "https://fr.wikipedia.org/wiki/Elisabeth_Rotten", "namede": "Elisabeth Rotten", "articlede": "https://de.wikipedia.org/wiki/Elisabeth_Rotten", "nameit": "", "articleit": "", "nameen": "Elisabeth Rotten", "articleen": "https://en.wikipedia.org/wiki/Elisabeth_Rotten", "instanceof": "http://www.wikidata.org/entity/Q5", "instanceofLabel": "\u00eatre humain", "gndid": "124382088"}], "wikidata_url": "http://www.wikidata.org/entity/Q96597", "wikipedia_page_title": null, "added_wikidata_wikipedia_to_text_links": true, "_initial": "R", "url": "https://hls-dhs-dss.ch/it/articles/009375/2010-11-16"}