{"search_result_name": "Koller, Arnold", "language": "fr", "id": "004739", "version": "2011-08-10", "_text": "Arnold Koller\n\n29.8.1933 \u00e0 Saint-Gall, cath., de Gossau (SG) et Oberb\u00fcren (SG), bourgeois d'honneur de Gossau (1987). Fils d'Arnold, instituteur, et de Genoveva Br\u00fclisauer. \u200bErika Brander, fille de Paul, chaudronnier. Coll\u00e8ge \u00e0 Appenzell, \u00e9tudes de sciences \u00e9conomiques \u00e0 la haute \u00e9cole de Saint-Gall (licence en 1957) et de droit \u00e0 l'universit\u00e9 de Fribourg, doctorat (1966), habilitation (1971), formation postgrade \u00e0 l'universit\u00e9 de Berkeley. Professeur extraordinaire (1972), puis ordinaire (1980) de droit \u00e9conomique et social europ\u00e9en et international \u00e0 la haute \u00e9cole de Saint-Gall. Conseiller national PDC d'Appenzell Rhodes-Int\u00e9rieures (1971-1986, pr\u00e9sident de son groupe 1980-1984, pr\u00e9sident du Conseil 1984-1985), K. a \u0153uvr\u00e9 dans divers domaines: r\u00e9f\u00e9rendum en mati\u00e8re d'accords internationaux, articles conjoncturels, participation, protection des consommateurs, droit des cartels et des soci\u00e9t\u00e9s anonymes, politique agricole. Pr\u00e9sident du tribunal cantonal des Rhodes-Int\u00e9rieures (1973-1986). Conseiller f\u00e9d\u00e9ral de 1987 \u00e0 1999, il dirigea d'abord le D\u00e9partement militaire, puis celui de justice et police d\u00e8s 1989, et fut pr\u00e9sident de la Conf\u00e9d\u00e9ration en 1990 et 1997. Il s'occupa entre autres de la nouvelle politique de s\u00e9curit\u00e9, de l'achat d'un nouveau fusil d'assaut et de l'avion de combat F/A-18, de la protection de l'Etat (affaire des fiches), du droit d'asile et de la r\u00e9vision totale de la Constitution (accept\u00e9e en votation en 1999). Pr\u00e9sident du Forum of Federations (d\u00e8s 2005; si\u00e8ge \u00e0 Ottawa). Docteur honoris causa de l'universit\u00e9 de Berne (2004). Lieutenant-colonel EMG.", "scraper_version": "0.2.0", "tags": [{"tag": "Politique (1848-) / Etat f\u00e9d\u00e9ral / Conseil f\u00e9d\u00e9ral", "url": "/fr/search/category?f_hls.lexicofacet_string=3/000100.124400.124500.124600."}, {"tag": "Politique (1848-) / Etat f\u00e9d\u00e9ral / Conseil national", "url": "/fr/search/category?f_hls.lexicofacet_string=3/000100.124400.124500.124800."}], "title": "Arnold Koller", "given_name": "Arnold", "family_name": "Koller", "authors_translators": ["Auteure/Auteur:\nHermann Bischofberger\nTraduction:\nAndr\u00e9 Naon"], "sources": {"Bibliographie": [{"text": "Altermatt, Conseil f\u00e9d\u00e9ral, 614", "author": ["Altermatt"], "tpub": ["Conseil f\u00e9d\u00e9ral"]}, {"text": "C. Schmid-Sutter, \u00abW\u00fcrdigung\u00bb, in Recht, Staat und Politik am Ende des zweiten Jahrtausends, \u00e9d. W.L. Schluep et al., 1993, 13-22", "author": ["C. Schmid-Sutter"], "tpub": ["W\u00fcrdigung", "Recht, Staat und Politik am Ende des zweiten Jahrtausends"]}, {"text": "K.H. Burmeister, 100 Jahre HSG, 1997, 136, 161, 205, 207-208, 235, 250, 288 (avec liste des \u0153uvres)", "author": ["K.H. Burmeister"], "tpub": ["100 Jahre HSG"]}]}, "metagrid_id": "4739", "metagrid_links": [{"Dodis": {"url": "https://dodis.ch/P28407", "short_description": "Documents diplomatiques suisses", "long_description": "Documents diplomatiques suisses"}, "Elites suisses": {"url": "https://www2.unil.ch/elitessuisses/index.php?page=detailPerso&idIdentite=55072", "short_description": "Elites suisses au XXe si\u00e8cle", "long_description": "Elites suisses au XXe si\u00e8cle"}, "BHS": {"url": "https://www.bsg.nb.admin.ch/discovery/search?query=lds50,contains,120733617&vid=41SNL_54_INST:bsg", "short_description": "Bibliographie de l'histoire suisse", "long_description": "Bibliographie de l'histoire suisse"}, "parl.ch": {"url": "https://www.parlament.ch/de/biografie?CouncillorId=426", "short_description": "Members of the Swiss parliament", "long_description": "Members of the Swiss National Council and the Council of States since 1848"}}], "notice_links": [{"title": "GND", "url": "http://d-nb.info/gnd/120733617"}, {"title": "VIAF", "url": "http://viaf.org/viaf/66575330"}], "bref": [{"title": "Dates biographiques", "text": "\u2217\ufe0e 29.8.1933\n1933-08-29", "birth_date": "1933-08-29"}], "birth_date": "1933-08-29", "text_blocks": [["h1", "Arnold Koller"], ["p", "29.8.1933 \u00e0 Saint-Gall, cath., de Gossau (SG) et Oberb\u00fcren (SG), bourgeois d'honneur de Gossau (1987). Fils d'Arnold, instituteur, et de Genoveva Br\u00fclisauer. \u200bErika Brander, fille de Paul, chaudronnier. Coll\u00e8ge \u00e0 Appenzell, \u00e9tudes de sciences \u00e9conomiques \u00e0 la haute \u00e9cole de Saint-Gall (licence en 1957) et de droit \u00e0 l'universit\u00e9 de Fribourg, doctorat (1966), habilitation (1971), formation postgrade \u00e0 l'universit\u00e9 de Berkeley. Professeur extraordinaire (1972), puis ordinaire (1980) de droit \u00e9conomique et social europ\u00e9en et international \u00e0 la haute \u00e9cole de Saint-Gall. Conseiller national PDC d'Appenzell Rhodes-Int\u00e9rieures (1971-1986, pr\u00e9sident de son groupe 1980-1984, pr\u00e9sident du Conseil 1984-1985), K. a \u0153uvr\u00e9 dans divers domaines: r\u00e9f\u00e9rendum en mati\u00e8re d'accords internationaux, articles conjoncturels, participation, protection des consommateurs, droit des cartels et des soci\u00e9t\u00e9s anonymes, politique agricole. Pr\u00e9sident du tribunal cantonal des Rhodes-Int\u00e9rieures (1973-1986). Conseiller f\u00e9d\u00e9ral de 1987 \u00e0 1999, il dirigea d'abord le D\u00e9partement militaire, puis celui de justice et police d\u00e8s 1989, et fut pr\u00e9sident de la Conf\u00e9d\u00e9ration en 1990 et 1997. Il s'occupa entre autres de la nouvelle politique de s\u00e9curit\u00e9, de l'achat d'un nouveau fusil d'assaut et de l'avion de combat F/A-18, de la protection de l'Etat (affaire des fiches), du droit d'asile et de la r\u00e9vision totale de la Constitution (accept\u00e9e en votation en 1999). Pr\u00e9sident du Forum of Federations (d\u00e8s 2005; si\u00e8ge \u00e0 Ottawa). Docteur honoris causa de l'universit\u00e9 de Berne (2004). Lieutenant-colonel EMG."]], "text_links": [[{"start": 0, "end": 13, "mention": null, "origin": "entity_fishing", "annotation": {"wikidata_entity_id": "Q115559", "wikipedia_page_id": 375206, "wikipedia_page_title": null, "wikidata_entity_url": "http://www.wikidata.org/entity/Q115559", "grobid_tag": null, "extra_fields": {"rawName": "EMG", "confidence_score": 0, "domains": ["Military"], "origin": "entity_fishing"}}, "href": "fr/articles/004739", "dhsid": "004739", "wiki": {"item": "http://www.wikidata.org/entity/Q115559", "itemLabel": "Arnold Koller", "dhsid": "004739", "namefr": "Arnold Koller", "articlefr": "https://fr.wikipedia.org/wiki/Arnold_Koller", "namede": "Arnold Koller", "articlede": "https://de.wikipedia.org/wiki/Arnold_Koller", "nameit": "Arnold Koller", "articleit": "https://it.wikipedia.org/wiki/Arnold_Koller", "nameen": "Arnold Koller", "articleen": "https://en.wikipedia.org/wiki/Arnold_Koller", "instanceof": "http://www.wikidata.org/entity/Q5", "instanceofLabel": "\u00eatre humain", "gndid": "120733617", "wikidata_id": "Q115559"}}], [{"start": 12, "end": 22, "mention": null, "origin": "entity_fishing", "annotation": {"wikidata_entity_id": "Q25607", "wikipedia_page_id": 123681, "wikipedia_page_title": null, "wikidata_entity_url": "http://www.wikidata.org/entity/Q25607", "grobid_tag": null, "extra_fields": {"rawName": "EMG", "confidence_score": 0, "domains": ["Military"], "origin": "entity_fishing"}}, "href": "fr/articles/001321", "dhsid": "001321", "wiki": {"item": "http://www.wikidata.org/entity/Q25607", "itemLabel": "Saint-Gall", "dhsid": "001321", "namefr": "Saint-Gall", "articlefr": "https://fr.wikipedia.org/wiki/Saint-Gall", "namede": "St. Gallen", "articlede": "https://de.wikipedia.org/wiki/St._Gallen", "nameit": "San Gallo", "articleit": "https://it.wikipedia.org/wiki/San_Gallo", "nameen": "St. Gallen", "articleen": "https://en.wikipedia.org/wiki/St._Gallen", "instanceof": "http://www.wikidata.org/entity/Q1187811", "instanceofLabel": "ville universitaire", "gndid": "4051594-1", "wikidata_id": "Q25607"}}, {"start": 34, "end": 40, "mention": null, "origin": "entity_fishing", "annotation": {"wikidata_entity_id": "Q69777", "wikipedia_page_id": 290241, "wikipedia_page_title": null, "wikidata_entity_url": "http://www.wikidata.org/entity/Q69777", "grobid_tag": null, "extra_fields": {"rawName": "EMG", "confidence_score": 0, "domains": ["Military"], "origin": "entity_fishing"}}, "href": "fr/articles/001407", "dhsid": "001407", "wiki": {"item": "http://www.wikidata.org/entity/Q69777", "itemLabel": "Gossau", "dhsid": "001407", "namefr": "Gossau (Saint-Gall)", "articlefr": "https://fr.wikipedia.org/wiki/Gossau_(Saint-Gall)", "namede": "Gossau SG", "articlede": "https://de.wikipedia.org/wiki/Gossau_SG", "nameit": "Gossau (San Gallo)", "articleit": "https://it.wikipedia.org/wiki/Gossau_(San_Gallo)", "nameen": "Gossau, St. Gallen", "articleen": "https://en.wikipedia.org/wiki/Gossau,_St._Gallen", "instanceof": "http://www.wikidata.org/entity/Q70208", "instanceofLabel": "commune de Suisse", "gndid": "4021646-9", "wikidata_id": "Q69777"}}, {"start": 42, "end": 44, "mention": null, "origin": "entity_fishing", "annotation": {"wikidata_entity_id": null, "wikipedia_page_id": null, "wikipedia_page_title": null, "wikidata_entity_url": null, "grobid_tag": "BUSINESS", "extra_fields": {"rawName": "EMG", "confidence_score": 0, "domains": ["Military"], "origin": "entity_fishing"}}}, {"start": 49, "end": 58, "mention": null, "origin": "entity_fishing", "annotation": {"wikidata_entity_id": "Q66670", "wikipedia_page_id": 285389, "wikipedia_page_title": null, "wikidata_entity_url": "http://www.wikidata.org/entity/Q66670", "grobid_tag": null, "extra_fields": {"rawName": "EMG", "confidence_score": 0, "domains": ["Military"], "origin": "entity_fishing"}}, "href": "fr/articles/001402", "dhsid": "001402", "wiki": {"item": "http://www.wikidata.org/entity/Q66670", "itemLabel": "Oberb\u00fcren", "dhsid": "001402", "namefr": "Oberb\u00fcren", "articlefr": "https://fr.wikipedia.org/wiki/Oberb%C3%BCren", "namede": "Oberb\u00fcren", "articlede": "https://de.wikipedia.org/wiki/Oberb%C3%BCren", "nameit": "Oberb\u00fcren", "articleit": "https://it.wikipedia.org/wiki/Oberb%C3%BCren", "nameen": "Oberb\u00fcren", "articleen": "https://en.wikipedia.org/wiki/Oberb%C3%BCren", "instanceof": "http://www.wikidata.org/entity/Q70208", "instanceofLabel": "commune de Suisse", "gndid": "4245376-8", "wikidata_id": "Q66670"}}, {"start": 60, "end": 62, "mention": null, "origin": "entity_fishing", "annotation": {"wikidata_entity_id": null, "wikipedia_page_id": null, "wikipedia_page_title": null, "wikidata_entity_url": null, "grobid_tag": "BUSINESS", "extra_fields": {"rawName": "EMG", "confidence_score": 0, "domains": ["Military"], "origin": "entity_fishing"}}}, {"start": 88, "end": 94, "mention": null, "origin": "entity_fishing", "annotation": {"wikidata_entity_id": "Q69777", "wikipedia_page_id": 290241, "wikipedia_page_title": null, "wikidata_entity_url": "http://www.wikidata.org/entity/Q69777", "grobid_tag": null, "extra_fields": {"rawName": "EMG", "confidence_score": 0, "domains": ["Military"], "origin": "entity_fishing"}}, "href": "fr/articles/001407", "dhsid": "001407", "wiki": {"item": "http://www.wikidata.org/entity/Q69777", "itemLabel": "Gossau", "dhsid": "001407", "namefr": "Gossau (Saint-Gall)", "articlefr": "https://fr.wikipedia.org/wiki/Gossau_(Saint-Gall)", "namede": "Gossau SG", "articlede": "https://de.wikipedia.org/wiki/Gossau_SG", "nameit": "Gossau (San Gallo)", "articleit": "https://it.wikipedia.org/wiki/Gossau_(San_Gallo)", "nameen": "Gossau, St. Gallen", "articleen": "https://en.wikipedia.org/wiki/Gossau,_St._Gallen", "instanceof": "http://www.wikidata.org/entity/Q70208", "instanceofLabel": "commune de Suisse", "gndid": "4021646-9", "wikidata_id": "Q69777"}}, {"start": 103, "end": 116, "mention": null, "origin": "entity_fishing", "annotation": {"wikidata_entity_id": null, "wikipedia_page_id": null, "wikipedia_page_title": null, "wikidata_entity_url": null, "grobid_tag": "PERSON", "extra_fields": {"rawName": "EMG", "confidence_score": 0, "domains": ["Military"], "origin": "entity_fishing"}}}, {"start": 137, "end": 156, "mention": null, "origin": "entity_fishing", "annotation": {"wikidata_entity_id": null, "wikipedia_page_id": null, "wikipedia_page_title": null, "wikidata_entity_url": null, "grobid_tag": "PERSON", "extra_fields": {"rawName": "EMG", "confidence_score": 0, "domains": ["Military"], "origin": "entity_fishing"}}}, {"start": 183, "end": 187, "mention": null, "origin": "entity_fishing", "annotation": {"wikidata_entity_id": null, "wikipedia_page_id": null, "wikipedia_page_title": null, "wikidata_entity_url": null, "grobid_tag": "PERSON", "extra_fields": {"rawName": "EMG", "confidence_score": 0, "domains": ["Military"], "origin": "entity_fishing"}}}, {"start": 213, "end": 222, "mention": null, "origin": "entity_fishing", "annotation": {"wikidata_entity_id": null, "wikipedia_page_id": null, "wikipedia_page_title": null, "wikidata_entity_url": null, "grobid_tag": "BUSINESS", "extra_fields": {"rawName": "EMG", "confidence_score": 0, "domains": ["Military"], "origin": "entity_fishing"}}}, {"start": 234, "end": 254, "mention": null, "origin": "entity_fishing", "annotation": {"wikidata_entity_id": "Q8134", "wikipedia_page_id": 3390, "wikipedia_page_title": null, "wikidata_entity_url": "http://www.wikidata.org/entity/Q8134", "grobid_tag": null, "extra_fields": {"rawName": "EMG", "confidence_score": 0, "domains": ["Military"], "origin": "entity_fishing"}}}, {"start": 275, "end": 285, "mention": null, "origin": "entity_fishing", "annotation": {"wikidata_entity_id": "Q25607", "wikipedia_page_id": 123681, "wikipedia_page_title": null, "wikidata_entity_url": "http://www.wikidata.org/entity/Q25607", "grobid_tag": null, "extra_fields": {"rawName": "EMG", "confidence_score": 0, "domains": ["Military"], "origin": "entity_fishing"}}, "href": "fr/articles/001321", "dhsid": "001321", "wiki": {"item": "http://www.wikidata.org/entity/Q25607", "itemLabel": "Saint-Gall", "dhsid": "001321", "namefr": "Saint-Gall", "articlefr": "https://fr.wikipedia.org/wiki/Saint-Gall", "namede": "St. Gallen", "articlede": "https://de.wikipedia.org/wiki/St._Gallen", "nameit": "San Gallo", "articleit": "https://it.wikipedia.org/wiki/San_Gallo", "nameen": "St. Gallen", "articleen": "https://en.wikipedia.org/wiki/St._Gallen", "instanceof": "http://www.wikidata.org/entity/Q1187811", "instanceofLabel": "ville universitaire", "gndid": "4051594-1", "wikidata_id": "Q25607"}}, {"start": 320, "end": 342, "mention": null, "origin": "entity_fishing", "annotation": {"wikidata_entity_id": "Q36188", "wikipedia_page_id": 118414, "wikipedia_page_title": null, "wikidata_entity_url": "http://www.wikidata.org/entity/Q36188", "grobid_tag": null, "extra_fields": {"rawName": "EMG", "confidence_score": 0, "domains": ["Military"], "origin": "entity_fishing"}}, "href": "fr/articles/010973", "dhsid": "010973", "wiki": {"item": "http://www.wikidata.org/entity/Q36188", "itemLabel": "Universit\u00e9 de Fribourg", "dhsid": "010973", "namefr": "Universit\u00e9 de Fribourg", "articlefr": "https://fr.wikipedia.org/wiki/Universit%C3%A9_de_Fribourg", "namede": "Universit\u00e4t Freiburg (Schweiz)", "articlede": "https://de.wikipedia.org/wiki/Universit%C3%A4t_Freiburg_(Schweiz)", "nameit": "Universit\u00e0 di Friburgo", "articleit": "https://it.wikipedia.org/wiki/Universit%C3%A0_di_Friburgo", "nameen": "University of Fribourg", "articleen": "https://en.wikipedia.org/wiki/University_of_Fribourg", "instanceof": "http://www.wikidata.org/entity/Q1767829", "instanceofLabel": "Q1767829", "gndid": "2024211-6", "wikidata_id": "Q36188"}}, {"start": 344, "end": 352, "mention": null, "origin": "entity_fishing", "annotation": {"wikidata_entity_id": "Q849697", "wikipedia_page_id": 51205, "wikipedia_page_title": null, "wikidata_entity_url": "http://www.wikidata.org/entity/Q849697", "grobid_tag": null, "extra_fields": {"rawName": "EMG", "confidence_score": 0, "domains": ["Military"], "origin": "entity_fishing"}}}, {"start": 361, "end": 373, "mention": null, "origin": "entity_fishing", "annotation": {"wikidata_entity_id": "Q308678", "wikipedia_page_id": 130875, "wikipedia_page_title": null, "wikidata_entity_url": "http://www.wikidata.org/entity/Q308678", "grobid_tag": null, "extra_fields": {"rawName": "EMG", "confidence_score": 0, "domains": ["Military"], "origin": "entity_fishing"}}}, {"start": 406, "end": 428, "mention": null, "origin": "entity_fishing", "annotation": {"wikidata_entity_id": "Q168756", "wikipedia_page_id": 5333, "wikipedia_page_title": null, "wikidata_entity_url": "http://www.wikidata.org/entity/Q168756", "grobid_tag": null, "extra_fields": {"rawName": "EMG", "confidence_score": 0, "domains": ["Military"], "origin": "entity_fishing"}}}, {"start": 506, "end": 541, "mention": null, "origin": "entity_fishing", "annotation": {"wikidata_entity_id": null, "wikipedia_page_id": null, "wikipedia_page_title": null, "wikidata_entity_url": null, "grobid_tag": "ORGANISATION", "extra_fields": {"rawName": "EMG", "confidence_score": 0, "domains": ["Military"], "origin": "entity_fishing"}}}, {"start": 562, "end": 572, "mention": null, "origin": "entity_fishing", "annotation": {"wikidata_entity_id": "Q25607", "wikipedia_page_id": 123681, "wikipedia_page_title": null, "wikidata_entity_url": "http://www.wikidata.org/entity/Q25607", "grobid_tag": null, "extra_fields": {"rawName": "EMG", "confidence_score": 0, "domains": ["Military"], "origin": "entity_fishing"}}, "href": "fr/articles/001321", "dhsid": "001321", "wiki": {"item": "http://www.wikidata.org/entity/Q25607", "itemLabel": "Saint-Gall", "dhsid": "001321", "namefr": "Saint-Gall", "articlefr": "https://fr.wikipedia.org/wiki/Saint-Gall", "namede": "St. Gallen", "articlede": "https://de.wikipedia.org/wiki/St._Gallen", "nameit": "San Gallo", "articleit": "https://it.wikipedia.org/wiki/San_Gallo", "nameen": "St. Gallen", "articleen": "https://en.wikipedia.org/wiki/St._Gallen", "instanceof": "http://www.wikidata.org/entity/Q1187811", "instanceofLabel": "ville universitaire", "gndid": "4051594-1", "wikidata_id": "Q25607"}}, {"start": 574, "end": 593, "mention": null, "origin": "entity_fishing", "annotation": {"wikidata_entity_id": "Q676078", "wikipedia_page_id": 54027, "wikipedia_page_title": null, "wikidata_entity_url": "http://www.wikidata.org/entity/Q676078", "grobid_tag": null, "extra_fields": {"rawName": "EMG", "confidence_score": 0, "domains": ["Military"], "origin": "entity_fishing"}}}, {"start": 594, "end": 597, "mention": null, "origin": "entity_fishing", "annotation": {"wikidata_entity_id": "Q659461", "wikipedia_page_id": 166473, "wikipedia_page_title": null, "wikidata_entity_url": "http://www.wikidata.org/entity/Q659461", "grobid_tag": null, "extra_fields": {"rawName": "EMG", "confidence_score": 0, "domains": ["Military"], "origin": "entity_fishing"}}, "href": "fr/articles/017377", "dhsid": "017377", "wiki": {"item": "http://www.wikidata.org/entity/Q659461", "itemLabel": "Parti d\u00e9mocrate-chr\u00e9tien", "dhsid": "017377", "namefr": "Parti d\u00e9mocrate-chr\u00e9tien (Suisse)", "articlefr": "https://fr.wikipedia.org/wiki/Parti_d%C3%A9mocrate-chr%C3%A9tien_(Suisse)", "namede": "Christlichdemokratische Volkspartei", "articlede": "https://de.wikipedia.org/wiki/Christlichdemokratische_Volkspartei", "nameit": "Partito Popolare Democratico (Svizzera)", "articleit": "https://it.wikipedia.org/wiki/Partito_Popolare_Democratico_(Svizzera)", "nameen": "Christian Democratic People's Party of Switzerland", "articleen": "https://en.wikipedia.org/wiki/Christian_Democratic_People%27s_Party_of_Switzerland", "instanceof": "http://www.wikidata.org/entity/Q7278", "instanceofLabel": "parti politique", "gndid": "43772-4", "wikidata_id": "Q659461"}}, {"start": 600, "end": 628, "mention": null, "origin": "entity_fishing", "annotation": {"wikidata_entity_id": "Q12094", "wikipedia_page_id": 12248, "wikipedia_page_title": null, "wikidata_entity_url": "http://www.wikidata.org/entity/Q12094", "grobid_tag": null, "extra_fields": {"rawName": "EMG", "confidence_score": 0, "domains": ["Military"], "origin": "entity_fishing"}}, "href": "fr/articles/007475", "dhsid": "007475", "wiki": {"item": "http://www.wikidata.org/entity/Q12094", "itemLabel": "canton d'Appenzell Rhodes-Int\u00e9rieures", "dhsid": "007475", "namefr": "Canton d'Appenzell Rhodes-Int\u00e9rieures", "articlefr": "https://fr.wikipedia.org/wiki/Canton_d%27Appenzell_Rhodes-Int%C3%A9rieures", "namede": "Kanton Appenzell Innerrhoden", "articlede": "https://de.wikipedia.org/wiki/Kanton_Appenzell_Innerrhoden", "nameit": "Canton Appenzello Interno", "articleit": "https://it.wikipedia.org/wiki/Canton_Appenzello_Interno", "nameen": "Appenzell Innerrhoden", "articleen": "https://en.wikipedia.org/wiki/Appenzell_Innerrhoden", "instanceof": "http://www.wikidata.org/entity/Q23058", "instanceofLabel": "canton de la Suisse", "gndid": "4002489-1", "wikidata_id": "Q12094"}}, {"start": 676, "end": 696, "mention": null, "origin": "entity_fishing", "annotation": {"wikidata_entity_id": "Q3409212", "wikipedia_page_id": 5716420, "wikipedia_page_title": null, "wikidata_entity_url": "http://www.wikidata.org/entity/Q3409212", "grobid_tag": null, "extra_fields": {"rawName": "EMG", "confidence_score": 0, "domains": ["Military"], "origin": "entity_fishing"}}}, {"start": 709, "end": 711, "mention": null, "origin": "entity_fishing", "annotation": {"wikidata_entity_id": "Q115559", "wikipedia_page_id": 375206, "wikipedia_page_title": null, "wikidata_entity_url": "http://www.wikidata.org/entity/Q115559", "grobid_tag": null, "extra_fields": {"rawName": "EMG", "confidence_score": 0, "domains": ["Military"], "origin": "entity_fishing"}}, "href": "fr/articles/004739", "dhsid": "004739", "wiki": {"item": "http://www.wikidata.org/entity/Q115559", "itemLabel": "Arnold Koller", "dhsid": "004739", "namefr": "Arnold Koller", "articlefr": "https://fr.wikipedia.org/wiki/Arnold_Koller", "namede": "Arnold Koller", "articlede": "https://de.wikipedia.org/wiki/Arnold_Koller", "nameit": "Arnold Koller", "articleit": "https://it.wikipedia.org/wiki/Arnold_Koller", "nameen": "Arnold Koller", "articleen": "https://en.wikipedia.org/wiki/Arnold_Koller", "instanceof": "http://www.wikidata.org/entity/Q5", "instanceofLabel": "\u00eatre humain", "gndid": "120733617", "wikidata_id": "Q115559"}}, {"start": 742, "end": 752, "mention": null, "origin": "entity_fishing", "annotation": {"wikidata_entity_id": "Q43109", "wikipedia_page_id": 46291, "wikipedia_page_title": null, "wikidata_entity_url": "http://www.wikidata.org/entity/Q43109", "grobid_tag": null, "extra_fields": {"rawName": "EMG", "confidence_score": 0, "domains": ["Military"], "origin": "entity_fishing"}}, "href": "fr/articles/010387", "dhsid": "010387", "wiki": {"item": "http://www.wikidata.org/entity/Q43109", "itemLabel": "r\u00e9f\u00e9rendum", "dhsid": "010387", "namefr": "R\u00e9f\u00e9rendum", "articlefr": "https://fr.wikipedia.org/wiki/R%C3%A9f%C3%A9rendum", "namede": "Referendum", "articlede": "https://de.wikipedia.org/wiki/Referendum", "nameit": "Referendum", "articleit": "https://it.wikipedia.org/wiki/Referendum", "nameen": "Referendum", "articleen": "https://en.wikipedia.org/wiki/Referendum", "instanceof": "http://www.wikidata.org/entity/Q74817647", "instanceofLabel": "aspect dans une r\u00e9gion g\u00e9ographique", "gndid": "", "wikidata_id": "Q43109"}}, {"start": 884, "end": 901, "mention": null, "origin": "entity_fishing", "annotation": {"wikidata_entity_id": "Q166280", "wikipedia_page_id": 3144724, "wikipedia_page_title": null, "wikidata_entity_url": "http://www.wikidata.org/entity/Q166280", "grobid_tag": null, "extra_fields": {"rawName": "EMG", "confidence_score": 0, "domains": ["Military"], "origin": "entity_fishing"}}}, {"start": 923, "end": 976, "mention": null, "origin": "entity_fishing", "annotation": {"wikidata_entity_id": null, "wikipedia_page_id": null, "wikipedia_page_title": null, "wikidata_entity_url": null, "grobid_tag": "ORGANISATION", "extra_fields": {"rawName": "EMG", "confidence_score": 0, "domains": ["Military"], "origin": "entity_fishing"}}}, {"start": 990, "end": 1008, "mention": null, "origin": "entity_fishing", "annotation": {"wikidata_entity_id": "Q30917", "wikipedia_page_id": 7673, "wikipedia_page_title": null, "wikidata_entity_url": "http://www.wikidata.org/entity/Q30917", "grobid_tag": null, "extra_fields": {"rawName": "EMG", "confidence_score": 0, "domains": ["Military"], "origin": "entity_fishing"}}, "href": "fr/articles/010085", "dhsid": "010085", "wiki": {"item": "http://www.wikidata.org/entity/Q30917", "itemLabel": "Conseil f\u00e9d\u00e9ral", "dhsid": "010085", "namefr": "Conseil f\u00e9d\u00e9ral (Suisse)", "articlefr": "https://fr.wikipedia.org/wiki/Conseil_f%C3%A9d%C3%A9ral_(Suisse)", "namede": "Bundesrat (Schweiz)", "articlede": "https://de.wikipedia.org/wiki/Bundesrat_(Schweiz)", "nameit": "Consiglio federale (Svizzera)", "articleit": "https://it.wikipedia.org/wiki/Consiglio_federale_(Svizzera)", "nameen": "Federal Council (Switzerland)", "articleen": "https://en.wikipedia.org/wiki/Federal_Council_(Switzerland)", "instanceof": "http://www.wikidata.org/entity/Q22950320", "instanceofLabel": "direction d'\u00c9tat collective", "gndid": "37888-4", "wikidata_id": "Q30917"}}, {"start": 1047, "end": 1068, "mention": null, "origin": "entity_fishing", "annotation": {"wikidata_entity_id": "Q667135", "wikipedia_page_id": 902678, "wikipedia_page_title": null, "wikidata_entity_url": "http://www.wikidata.org/entity/Q667135", "grobid_tag": null, "extra_fields": {"rawName": "EMG", "confidence_score": 0, "domains": ["Military"], "origin": "entity_fishing"}}}, {"start": 1119, "end": 1148, "mention": null, "origin": "entity_fishing", "annotation": {"wikidata_entity_id": "Q688230", "wikipedia_page_id": 218796, "wikipedia_page_title": null, "wikidata_entity_url": "http://www.wikidata.org/entity/Q688230", "grobid_tag": null, "extra_fields": {"rawName": "EMG", "confidence_score": 0, "domains": ["Military"], "origin": "entity_fishing"}}, "href": "fr/articles/010086", "dhsid": "010086", "wiki": {"item": "http://www.wikidata.org/entity/Q688230", "itemLabel": "Pr\u00e9sident de la Conf\u00e9d\u00e9ration suisse", "dhsid": "010086", "namefr": "Pr\u00e9sident de la Conf\u00e9d\u00e9ration suisse", "articlefr": "https://fr.wikipedia.org/wiki/Pr%C3%A9sident_de_la_Conf%C3%A9d%C3%A9ration_suisse", "namede": "Bundespr\u00e4sident (Schweiz)", "articlede": "https://de.wikipedia.org/wiki/Bundespr%C3%A4sident_(Schweiz)", "nameit": "Presidente della Confederazione svizzera", "articleit": "https://it.wikipedia.org/wiki/Presidente_della_Confederazione_svizzera", "nameen": "President of the Swiss Confederation", "articleen": "https://en.wikipedia.org/wiki/President_of_the_Swiss_Confederation", "instanceof": "http://www.wikidata.org/entity/Q4164871", "instanceofLabel": "fonction", "gndid": "", "wikidata_id": "Q688230"}}, {"start": 1253, "end": 1267, "mention": null, "origin": "entity_fishing", "annotation": {"wikidata_entity_id": "Q177456", "wikipedia_page_id": 75849, "wikipedia_page_title": null, "wikidata_entity_url": "http://www.wikidata.org/entity/Q177456", "grobid_tag": null, "extra_fields": {"rawName": "EMG", "confidence_score": 0, "domains": ["Military"], "origin": "entity_fishing"}}}, {"start": 1276, "end": 1291, "mention": null, "origin": "entity_fishing", "annotation": {"wikidata_entity_id": "Q216916", "wikipedia_page_id": 50339, "wikipedia_page_title": null, "wikidata_entity_url": "http://www.wikidata.org/entity/Q216916", "grobid_tag": null, "extra_fields": {"rawName": "EMG", "confidence_score": 0, "domains": ["Military"], "origin": "entity_fishing"}}}, {"start": 1292, "end": 1298, "mention": null, "origin": "entity_fishing", "annotation": {"wikidata_entity_id": "Q46397", "wikipedia_page_id": 102136, "wikipedia_page_title": null, "wikidata_entity_url": "http://www.wikidata.org/entity/Q46397", "grobid_tag": null, "extra_fields": {"rawName": "EMG", "confidence_score": 0, "domains": ["Military"], "origin": "entity_fishing"}}}, {"start": 1328, "end": 1346, "mention": null, "origin": "entity_fishing", "annotation": {"wikidata_entity_id": "Q2825979", "wikipedia_page_id": 45864, "wikipedia_page_title": null, "wikidata_entity_url": "http://www.wikidata.org/entity/Q2825979", "grobid_tag": null, "extra_fields": {"rawName": "EMG", "confidence_score": 0, "domains": ["Military"], "origin": "entity_fishing"}}}, {"start": 1352, "end": 1365, "mention": null, "origin": "entity_fishing", "annotation": {"wikidata_entity_id": "Q11283415", "wikipedia_page_id": 1434706, "wikipedia_page_title": null, "wikidata_entity_url": "http://www.wikidata.org/entity/Q11283415", "grobid_tag": null, "extra_fields": {"rawName": "EMG", "confidence_score": 0, "domains": ["Military"], "origin": "entity_fishing"}}}, {"start": 1375, "end": 1409, "mention": null, "origin": "entity_fishing", "annotation": {"wikidata_entity_id": "Q1470214", "wikipedia_page_id": 4482633, "wikipedia_page_title": null, "wikidata_entity_url": "http://www.wikidata.org/entity/Q1470214", "grobid_tag": null, "extra_fields": {"rawName": "EMG", "confidence_score": 0, "domains": ["Military"], "origin": "entity_fishing"}}}, {"start": 1455, "end": 1475, "mention": null, "origin": "entity_fishing", "annotation": {"wikidata_entity_id": null, "wikipedia_page_id": null, "wikipedia_page_title": null, "wikidata_entity_url": null, "grobid_tag": "ORGANISATION", "extra_fields": {"rawName": "EMG", "confidence_score": 0, "domains": ["Military"], "origin": "entity_fishing"}}}, {"start": 1495, "end": 1501, "mention": null, "origin": "entity_fishing", "annotation": {"wikidata_entity_id": "Q1930", "wikipedia_page_id": 37867, "wikipedia_page_title": null, "wikidata_entity_url": "http://www.wikidata.org/entity/Q1930", "grobid_tag": null, "extra_fields": {"rawName": "EMG", "confidence_score": 0, "domains": ["Military"], "origin": "entity_fishing"}}}, {"start": 1504, "end": 1525, "mention": null, "origin": "entity_fishing", "annotation": {"wikidata_entity_id": "Q11415564", "wikipedia_page_id": 262562, "wikipedia_page_title": null, "wikidata_entity_url": "http://www.wikidata.org/entity/Q11415564", "grobid_tag": null, "extra_fields": {"rawName": "EMG", "confidence_score": 0, "domains": ["Military"], "origin": "entity_fishing"}}}, {"start": 1531, "end": 1550, "mention": null, "origin": "entity_fishing", "annotation": {"wikidata_entity_id": "Q659080", "wikipedia_page_id": 967260, "wikipedia_page_title": null, "wikidata_entity_url": "http://www.wikidata.org/entity/Q659080", "grobid_tag": null, "extra_fields": {"rawName": "EMG", "confidence_score": 0, "domains": ["Military"], "origin": "entity_fishing"}}, "href": "fr/articles/010972", "dhsid": "010972", "wiki": {"item": "http://www.wikidata.org/entity/Q659080", "itemLabel": "Universit\u00e9 de Berne", "dhsid": "010972", "namefr": "Universit\u00e9 de Berne", "articlefr": "https://fr.wikipedia.org/wiki/Universit%C3%A9_de_Berne", "namede": "Universit\u00e4t Bern", "articlede": "https://de.wikipedia.org/wiki/Universit%C3%A4t_Bern", "nameit": "Universit\u00e0 di Berna", "articleit": "https://it.wikipedia.org/wiki/Universit%C3%A0_di_Berna", "nameen": "University of Bern", "articleen": "https://en.wikipedia.org/wiki/University_of_Bern", "instanceof": "http://www.wikidata.org/entity/Q45400320", "instanceofLabel": "\u00e9diteur en acc\u00e8s libre", "gndid": "2023768-6", "wikidata_id": "Q659080"}}, {"start": 1559, "end": 1577, "mention": null, "origin": "entity_fishing", "annotation": {"wikidata_entity_id": "Q493898", "wikipedia_page_id": 87817, "wikipedia_page_title": null, "wikidata_entity_url": "http://www.wikidata.org/entity/Q493898", "grobid_tag": null, "extra_fields": {"rawName": "EMG", "confidence_score": 0, "domains": ["Military"], "origin": "entity_fishing"}}}, {"start": 1578, "end": 1581, "mention": null, "origin": "entity_fishing", "annotation": {"wikidata_entity_id": null, "wikipedia_page_id": null, "wikipedia_page_title": null, "wikidata_entity_url": null, "grobid_tag": "BUSINESS", "extra_fields": {"rawName": "EMG", "confidence_score": 0, "domains": ["Military"], "origin": "entity_fishing"}}}]], "wiki_links": [{"item": "http://www.wikidata.org/entity/Q115559", "itemLabel": "Arnold Koller", "dhsid": "004739", "namefr": "Arnold Koller", "articlefr": "https://fr.wikipedia.org/wiki/Arnold_Koller", "namede": "Arnold Koller", "articlede": "https://de.wikipedia.org/wiki/Arnold_Koller", "nameit": "Arnold Koller", "articleit": "https://it.wikipedia.org/wiki/Arnold_Koller", "nameen": "Arnold Koller", "articleen": "https://en.wikipedia.org/wiki/Arnold_Koller", "instanceof": "http://www.wikidata.org/entity/Q5", "instanceofLabel": "\u00eatre humain", "gndid": "120733617"}], "wikidata_url": "http://www.wikidata.org/entity/Q115559", "wikipedia_page_title": "Arnold Koller", "added_wikidata_wikipedia_to_text_links": true, "_initial": "K", "url": "https://hls-dhs-dss.ch/fr/articles/004739/2011-08-10"}