{"search_result_name": "Edelmann, Walter", "language": "fr", "id": "020339", "version": "2004-07-26", "_text": "Walter Edelmann\n\n12.5.1923 \u00e0 Zurzach, 8.3.2002 \u00e0 Zurzach, cath., de Muolen. Fils d'August, employ\u00e9 postal, et de Frieda Keller. \u200bMargrith Meyer, fille de Josef, directeur de la Rentenanstalt. Coll\u00e8ge \u00e0 Engelberg, \u00e9tudes de droit \u00e0 Zurich et Paris (doctorat en 1949). Brevets d'avocat et de notaire en 1950. Etude d'avocat et de notaire \u00e0 Zurzach. Pr\u00e9sident de la commune de Zurzach de 1957 \u00e0 1965. Membre conservateur du Grand Conseil argovien de 1957 \u00e0 1983 (pr\u00e9sident en 1969-1970), pr\u00e9sident de la commission des finances de 1965 \u00e0 1969 et de la commission de justice de 1977 \u00e0 1981. E. s'investit surtout en faveur de projets touchant \u00e0 la politique r\u00e9gionale du district de Zurzach. Premier pr\u00e9sident de Thermalquelle AG et, avec sa femme, cr\u00e9ateur d'une fondation pour les \u00e9tablissements thermaux, il fut un important promoteur du d\u00e9veloppement de Zurzach comme lieu de cure, d\u00e9veloppement qui commen\u00e7a \u00e0 son initiative en 1955 par le nouveau forage d'une source thermale d\u00e9couverte en 1914.", "scraper_version": "0.2.0", "tags": [{"tag": "Politique (1848-) / Cantons et communes / Parlement cantonal", "url": "/fr/search/category?f_hls.lexicofacet_string=3/000100.124400.125300.125500."}, {"tag": "Politique (1848-) / Cantons et communes / Pr\u00e9sidents de commune", "url": "/fr/search/category?f_hls.lexicofacet_string=3/000100.124400.125300.125600."}], "title": "Walter Edelmann", "given_name": "Walter", "family_name": "Edelmann", "authors_translators": ["Auteure/Auteur:\nAndreas Steigmeier\nTraduction:\nArthur Bissegger"], "sources": {"\u0152uvres": [{"text": "Bad Zurzach, 1991", "tpub": ["Bad Zurzach"]}], "Bibliographie": [{"text": "Protokoll des [aargauischen] Grossen Rats, 23.4.1969; 7.6.1983", "tpub": ["Protokoll des [aargauischen] Grossen Rats"]}]}, "metagrid_id": "20339", "metagrid_links": [{"Elites suisses": {"url": "https://www2.unil.ch/elitessuisses/index.php?page=detailPerso&idIdentite=61700", "short_description": "Elites suisses au XXe si\u00e8cle", "long_description": "Elites suisses au XXe si\u00e8cle"}}], "notice_links": [{"title": "GND", "url": "http://d-nb.info/gnd/1050112008"}, {"title": "VIAF", "url": "http://viaf.org/viaf/308194706"}], "bref": [{"title": "Dates biographiques", "text": "\u2217\ufe0e 12.5.1923\n   \u271d\ufe0e 8.3.2002\n1923-05-122002-03-08", "birth_date": "1923-05-12", "death_date": "2002-03-08"}], "birth_date": "1923-05-12", "death_date": "2002-03-08", "text_blocks": [["h1", "Walter Edelmann"], ["p", "12.5.1923 \u00e0 Zurzach, 8.3.2002 \u00e0 Zurzach, cath., de Muolen. Fils d'August, employ\u00e9 postal, et de Frieda Keller. \u200bMargrith Meyer, fille de Josef, directeur de la Rentenanstalt. Coll\u00e8ge \u00e0 Engelberg, \u00e9tudes de droit \u00e0 Zurich et Paris (doctorat en 1949). Brevets d'avocat et de notaire en 1950. Etude d'avocat et de notaire \u00e0 Zurzach. Pr\u00e9sident de la commune de Zurzach de 1957 \u00e0 1965. Membre conservateur du Grand Conseil argovien de 1957 \u00e0 1983 (pr\u00e9sident en 1969-1970), pr\u00e9sident de la commission des finances de 1965 \u00e0 1969 et de la commission de justice de 1977 \u00e0 1981. E. s'investit surtout en faveur de projets touchant \u00e0 la politique r\u00e9gionale du district de Zurzach. Premier pr\u00e9sident de Thermalquelle AG et, avec sa femme, cr\u00e9ateur d'une fondation pour les \u00e9tablissements thermaux, il fut un important promoteur du d\u00e9veloppement de Zurzach comme lieu de cure, d\u00e9veloppement qui commen\u00e7a \u00e0 son initiative en 1955 par le nouveau forage d'une source thermale d\u00e9couverte en 1914."]], "text_links": [[{"start": 0, "end": 15, "mention": null, "origin": "entity_fishing", "annotation": {"wikidata_entity_id": null, "wikipedia_page_id": null, "wikipedia_page_title": null, "wikidata_entity_url": null, "grobid_tag": "PERSON", "extra_fields": {"rawName": "forage", "confidence_score": 0.3606, "domains": ["Hydraulics", "Environment"], "origin": "entity_fishing"}}}], [{"start": 12, "end": 19, "mention": null, "origin": "entity_fishing", "annotation": {"wikidata_entity_id": "Q64186", "wikipedia_page_id": 219572, "wikipedia_page_title": null, "wikidata_entity_url": "http://www.wikidata.org/entity/Q64186", "grobid_tag": null, "extra_fields": {"rawName": "forage", "confidence_score": 0.3606, "domains": ["Hydraulics", "Environment"], "origin": "entity_fishing"}}, "href": "fr/articles/001851", "dhsid": "001851", "wiki": {"item": "http://www.wikidata.org/entity/Q64186", "itemLabel": "Bad Zurzach", "dhsid": "001851", "namefr": "Bad Zurzach", "articlefr": "https://fr.wikipedia.org/wiki/Bad_Zurzach", "namede": "Bad Zurzach", "articlede": "https://de.wikipedia.org/wiki/Bad_Zurzach", "nameit": "Bad Zurzach", "articleit": "https://it.wikipedia.org/wiki/Bad_Zurzach", "nameen": "Bad Zurzach", "articleen": "https://en.wikipedia.org/wiki/Bad_Zurzach", "instanceof": "http://www.wikidata.org/entity/Q902814", "instanceofLabel": "ville frontali\u00e8re", "gndid": "4068142-7", "wikidata_id": "Q64186"}}, {"start": 32, "end": 39, "mention": null, "origin": "entity_fishing", "annotation": {"wikidata_entity_id": "Q64186", "wikipedia_page_id": 219572, "wikipedia_page_title": null, "wikidata_entity_url": "http://www.wikidata.org/entity/Q64186", "grobid_tag": null, "extra_fields": {"rawName": "forage", "confidence_score": 0.3606, "domains": ["Hydraulics", "Environment"], "origin": "entity_fishing"}}, "href": "fr/articles/001851", "dhsid": "001851", "wiki": {"item": "http://www.wikidata.org/entity/Q64186", "itemLabel": "Bad Zurzach", "dhsid": "001851", "namefr": "Bad Zurzach", "articlefr": "https://fr.wikipedia.org/wiki/Bad_Zurzach", "namede": "Bad Zurzach", "articlede": "https://de.wikipedia.org/wiki/Bad_Zurzach", "nameit": "Bad Zurzach", "articleit": "https://it.wikipedia.org/wiki/Bad_Zurzach", "nameen": "Bad Zurzach", "articleen": "https://en.wikipedia.org/wiki/Bad_Zurzach", "instanceof": "http://www.wikidata.org/entity/Q902814", "instanceofLabel": "ville frontali\u00e8re", "gndid": "4068142-7", "wikidata_id": "Q64186"}}, {"start": 51, "end": 57, "mention": null, "origin": "entity_fishing", "annotation": {"wikidata_entity_id": "Q67044", "wikipedia_page_id": 290244, "wikipedia_page_title": null, "wikidata_entity_url": "http://www.wikidata.org/entity/Q67044", "grobid_tag": null, "extra_fields": {"rawName": "forage", "confidence_score": 0.3606, "domains": ["Hydraulics", "Environment"], "origin": "entity_fishing"}}, "href": "fr/articles/001320", "dhsid": "001320", "wiki": {"item": "http://www.wikidata.org/entity/Q67044", "itemLabel": "Muolen", "dhsid": "001320", "namefr": "Muolen", "articlefr": "https://fr.wikipedia.org/wiki/Muolen", "namede": "Muolen", "articlede": "https://de.wikipedia.org/wiki/Muolen", "nameit": "Muolen", "articleit": "https://it.wikipedia.org/wiki/Muolen", "nameen": "Muolen", "articleen": "https://en.wikipedia.org/wiki/Muolen", "instanceof": "http://www.wikidata.org/entity/Q70208", "instanceofLabel": "commune de Suisse", "gndid": "4647007-4", "wikidata_id": "Q67044"}}, {"start": 74, "end": 88, "mention": null, "origin": "entity_fishing", "annotation": {"wikidata_entity_id": "Q1307956", "wikipedia_page_id": 1340573, "wikipedia_page_title": null, "wikidata_entity_url": "http://www.wikidata.org/entity/Q1307956", "grobid_tag": null, "extra_fields": {"rawName": "forage", "confidence_score": 0.3606, "domains": ["Hydraulics", "Environment"], "origin": "entity_fishing"}}, "href": "fr/articles/027154", "dhsid": "027154", "wiki": {"item": "http://www.wikidata.org/entity/Q1307956", "itemLabel": "Postes, t\u00e9l\u00e9phones, t\u00e9l\u00e9graphes", "dhsid": "027154", "namefr": "Postes, t\u00e9l\u00e9phones, t\u00e9l\u00e9graphes (Suisse)", "articlefr": "https://fr.wikipedia.org/wiki/Postes,_t%C3%A9l%C3%A9phones,_t%C3%A9l%C3%A9graphes_(Suisse)", "namede": "Post-, Telefon- und Telegrafenbetriebe", "articlede": "https://de.wikipedia.org/wiki/Post-,_Telefon-_und_Telegrafenbetriebe", "nameit": "Poste, telefoni e telegrafi", "articleit": "https://it.wikipedia.org/wiki/Poste,_telefoni_e_telegrafi", "nameen": "Postal Telegraph and Telephone (Switzerland)", "articleen": "https://en.wikipedia.org/wiki/Postal_Telegraph_and_Telephone_(Switzerland)", "instanceof": "http://www.wikidata.org/entity/Q1252707", "instanceofLabel": "Services des postes, t\u00e9l\u00e9graphes et t\u00e9l\u00e9phones", "gndid": "", "wikidata_id": "Q1307956"}}, {"start": 96, "end": 126, "mention": null, "origin": "entity_fishing", "annotation": {"wikidata_entity_id": null, "wikipedia_page_id": null, "wikipedia_page_title": null, "wikidata_entity_url": null, "grobid_tag": "PERSON", "extra_fields": {"rawName": "forage", "confidence_score": 0.3606, "domains": ["Hydraulics", "Environment"], "origin": "entity_fishing"}}}, {"start": 137, "end": 142, "mention": null, "origin": "entity_fishing", "annotation": {"wikidata_entity_id": null, "wikipedia_page_id": null, "wikipedia_page_title": null, "wikidata_entity_url": null, "grobid_tag": "PERSON", "extra_fields": {"rawName": "forage", "confidence_score": 0.3606, "domains": ["Hydraulics", "Environment"], "origin": "entity_fishing"}}}, {"start": 160, "end": 173, "mention": null, "origin": "entity_fishing", "annotation": {"wikidata_entity_id": "Q667350", "wikipedia_page_id": 1064137, "wikipedia_page_title": null, "wikidata_entity_url": "http://www.wikidata.org/entity/Q667350", "grobid_tag": null, "extra_fields": {"rawName": "forage", "confidence_score": 0.3606, "domains": ["Hydraulics", "Environment"], "origin": "entity_fishing"}}, "href": "fr/articles/041816", "dhsid": "041816", "wiki": {"item": "http://www.wikidata.org/entity/Q667350", "itemLabel": "Swiss Life", "dhsid": "041816", "namefr": "Swiss Life", "articlefr": "https://fr.wikipedia.org/wiki/Swiss_Life", "namede": "Swiss Life", "articlede": "https://de.wikipedia.org/wiki/Swiss_Life", "nameit": "", "articleit": "", "nameen": "Swiss Life", "articleen": "https://en.wikipedia.org/wiki/Swiss_Life", "instanceof": "http://www.wikidata.org/entity/Q4830453", "instanceofLabel": "firme", "gndid": "10158355-2", "wikidata_id": "Q667350"}}, {"start": 185, "end": 194, "mention": null, "origin": "entity_fishing", "annotation": {"wikidata_entity_id": "Q64108", "wikipedia_page_id": 203479, "wikipedia_page_title": null, "wikidata_entity_url": "http://www.wikidata.org/entity/Q64108", "grobid_tag": null, "extra_fields": {"rawName": "forage", "confidence_score": 0.3606, "domains": ["Hydraulics", "Environment"], "origin": "entity_fishing"}}, "href": "fr/articles/000741", "dhsid": "000741", "wiki": {"item": "http://www.wikidata.org/entity/Q64108", "itemLabel": "Engelberg", "dhsid": "000741", "namefr": "Engelberg", "articlefr": "https://fr.wikipedia.org/wiki/Engelberg", "namede": "Engelberg", "articlede": "https://de.wikipedia.org/wiki/Engelberg", "nameit": "Engelberg", "articleit": "https://it.wikipedia.org/wiki/Engelberg", "nameen": "Engelberg", "articleen": "https://en.wikipedia.org/wiki/Engelberg", "instanceof": "http://www.wikidata.org/entity/Q70208", "instanceofLabel": "commune de Suisse", "gndid": "4014751-4", "wikidata_id": "Q64108"}}, {"start": 214, "end": 220, "mention": null, "origin": "entity_fishing", "annotation": {"wikidata_entity_id": "Q72", "wikipedia_page_id": 24229, "wikipedia_page_title": null, "wikidata_entity_url": "http://www.wikidata.org/entity/Q72", "grobid_tag": null, "extra_fields": {"rawName": "forage", "confidence_score": 0.3606, "domains": ["Hydraulics", "Environment"], "origin": "entity_fishing"}}, "href": "fr/articles/000171", "dhsid": "000171", "wiki": {"item": "http://www.wikidata.org/entity/Q72", "itemLabel": "Zurich", "dhsid": "000171", "namefr": "Zurich", "articlefr": "https://fr.wikipedia.org/wiki/Zurich", "namede": "Z\u00fcrich", "articlede": "https://de.wikipedia.org/wiki/Z%C3%BCrich", "nameit": "Zurigo", "articleit": "https://it.wikipedia.org/wiki/Zurigo", "nameen": "Z\u00fcrich", "articleen": "https://en.wikipedia.org/wiki/Z%C3%BCrich", "instanceof": "http://www.wikidata.org/entity/Q70208", "instanceofLabel": "commune de Suisse", "gndid": "4068038-1", "wikidata_id": "Q72"}}, {"start": 224, "end": 229, "mention": null, "origin": "entity_fishing", "annotation": {"wikidata_entity_id": "Q90", "wikipedia_page_id": 681159, "wikipedia_page_title": null, "wikidata_entity_url": "http://www.wikidata.org/entity/Q90", "grobid_tag": null, "extra_fields": {"rawName": "forage", "confidence_score": 0.3606, "domains": ["Hydraulics", "Environment"], "origin": "entity_fishing"}}, "href": "fr/articles/006604", "dhsid": "006604", "wiki": {"item": "http://www.wikidata.org/entity/Q90", "itemLabel": "Paris", "dhsid": "006604", "namefr": "Paris", "articlefr": "https://fr.wikipedia.org/wiki/Paris", "namede": "Paris", "articlede": "https://de.wikipedia.org/wiki/Paris", "nameit": "Parigi", "articleit": "https://it.wikipedia.org/wiki/Parigi", "nameen": "Paris", "articleen": "https://en.wikipedia.org/wiki/Paris", "instanceof": "http://www.wikidata.org/entity/Q22923920", "instanceofLabel": "collectivit\u00e9 territoriale fran\u00e7aise \u00e0 statut particulier", "gndid": "4044660-8", "wikidata_id": "Q90"}}, {"start": 231, "end": 239, "mention": null, "origin": "entity_fishing", "annotation": {"wikidata_entity_id": "Q849697", "wikipedia_page_id": 51205, "wikipedia_page_title": null, "wikidata_entity_url": "http://www.wikidata.org/entity/Q849697", "grobid_tag": null, "extra_fields": {"rawName": "forage", "confidence_score": 0.3606, "domains": ["Hydraulics", "Environment"], "origin": "entity_fishing"}}}, {"start": 260, "end": 266, "mention": null, "origin": "entity_fishing", "annotation": {"wikidata_entity_id": "Q40348", "wikipedia_page_id": 57147, "wikipedia_page_title": null, "wikidata_entity_url": "http://www.wikidata.org/entity/Q40348", "grobid_tag": null, "extra_fields": {"rawName": "forage", "confidence_score": 0.3606, "domains": ["Hydraulics", "Environment"], "origin": "entity_fishing"}}, "href": "fr/articles/009643", "dhsid": "009643", "wiki": {"item": "http://www.wikidata.org/entity/Q40348", "itemLabel": "avocat", "dhsid": "009643", "namefr": "Avocat (m\u00e9tier)", "articlefr": "https://fr.wikipedia.org/wiki/Avocat_(m%C3%A9tier)", "namede": "Rechtsanwalt", "articlede": "https://de.wikipedia.org/wiki/Rechtsanwalt", "nameit": "Avvocato", "articleit": "https://it.wikipedia.org/wiki/Avvocato", "nameen": "Lawyer", "articleen": "https://en.wikipedia.org/wiki/Lawyer", "instanceof": "http://www.wikidata.org/entity/Q15987302", "instanceofLabel": "profession juridique", "gndid": "4177191-6", "wikidata_id": "Q40348"}}, {"start": 273, "end": 280, "mention": null, "origin": "entity_fishing", "annotation": {"wikidata_entity_id": "Q189010", "wikipedia_page_id": 7703218, "wikipedia_page_title": null, "wikidata_entity_url": "http://www.wikidata.org/entity/Q189010", "grobid_tag": null, "extra_fields": {"rawName": "forage", "confidence_score": 0.3606, "domains": ["Hydraulics", "Environment"], "origin": "entity_fishing"}}}, {"start": 298, "end": 304, "mention": null, "origin": "entity_fishing", "annotation": {"wikidata_entity_id": "Q40348", "wikipedia_page_id": 57147, "wikipedia_page_title": null, "wikidata_entity_url": "http://www.wikidata.org/entity/Q40348", "grobid_tag": null, "extra_fields": {"rawName": "forage", "confidence_score": 0.3606, "domains": ["Hydraulics", "Environment"], "origin": "entity_fishing"}}, "href": "fr/articles/009643", "dhsid": "009643", "wiki": {"item": "http://www.wikidata.org/entity/Q40348", "itemLabel": "avocat", "dhsid": "009643", "namefr": "Avocat (m\u00e9tier)", "articlefr": "https://fr.wikipedia.org/wiki/Avocat_(m%C3%A9tier)", "namede": "Rechtsanwalt", "articlede": "https://de.wikipedia.org/wiki/Rechtsanwalt", "nameit": "Avvocato", "articleit": "https://it.wikipedia.org/wiki/Avvocato", "nameen": "Lawyer", "articleen": "https://en.wikipedia.org/wiki/Lawyer", "instanceof": "http://www.wikidata.org/entity/Q15987302", "instanceofLabel": "profession juridique", "gndid": "4177191-6", "wikidata_id": "Q40348"}}, {"start": 311, "end": 318, "mention": null, "origin": "entity_fishing", "annotation": {"wikidata_entity_id": "Q189010", "wikipedia_page_id": 7703218, "wikipedia_page_title": null, "wikidata_entity_url": "http://www.wikidata.org/entity/Q189010", "grobid_tag": null, "extra_fields": {"rawName": "forage", "confidence_score": 0.3606, "domains": ["Hydraulics", "Environment"], "origin": "entity_fishing"}}}, {"start": 321, "end": 328, "mention": null, "origin": "entity_fishing", "annotation": {"wikidata_entity_id": "Q64186", "wikipedia_page_id": 219572, "wikipedia_page_title": null, "wikidata_entity_url": "http://www.wikidata.org/entity/Q64186", "grobid_tag": null, "extra_fields": {"rawName": "forage", "confidence_score": 0.3606, "domains": ["Hydraulics", "Environment"], "origin": "entity_fishing"}}, "href": "fr/articles/001851", "dhsid": "001851", "wiki": {"item": "http://www.wikidata.org/entity/Q64186", "itemLabel": "Bad Zurzach", "dhsid": "001851", "namefr": "Bad Zurzach", "articlefr": "https://fr.wikipedia.org/wiki/Bad_Zurzach", "namede": "Bad Zurzach", "articlede": "https://de.wikipedia.org/wiki/Bad_Zurzach", "nameit": "Bad Zurzach", "articleit": "https://it.wikipedia.org/wiki/Bad_Zurzach", "nameen": "Bad Zurzach", "articleen": "https://en.wikipedia.org/wiki/Bad_Zurzach", "instanceof": "http://www.wikidata.org/entity/Q902814", "instanceofLabel": "ville frontali\u00e8re", "gndid": "4068142-7", "wikidata_id": "Q64186"}}, {"start": 357, "end": 364, "mention": null, "origin": "entity_fishing", "annotation": {"wikidata_entity_id": "Q64186", "wikipedia_page_id": 219572, "wikipedia_page_title": null, "wikidata_entity_url": "http://www.wikidata.org/entity/Q64186", "grobid_tag": null, "extra_fields": {"rawName": "forage", "confidence_score": 0.3606, "domains": ["Hydraulics", "Environment"], "origin": "entity_fishing"}}, "href": "fr/articles/001851", "dhsid": "001851", "wiki": {"item": "http://www.wikidata.org/entity/Q64186", "itemLabel": "Bad Zurzach", "dhsid": "001851", "namefr": "Bad Zurzach", "articlefr": "https://fr.wikipedia.org/wiki/Bad_Zurzach", "namede": "Bad Zurzach", "articlede": "https://de.wikipedia.org/wiki/Bad_Zurzach", "nameit": "Bad Zurzach", "articleit": "https://it.wikipedia.org/wiki/Bad_Zurzach", "nameen": "Bad Zurzach", "articleen": "https://en.wikipedia.org/wiki/Bad_Zurzach", "instanceof": "http://www.wikidata.org/entity/Q902814", "instanceofLabel": "ville frontali\u00e8re", "gndid": "4068142-7", "wikidata_id": "Q64186"}}, {"start": 381, "end": 400, "mention": null, "origin": "entity_fishing", "annotation": {"wikidata_entity_id": "Q909827", "wikipedia_page_id": 559700, "wikipedia_page_title": null, "wikidata_entity_url": "http://www.wikidata.org/entity/Q909827", "grobid_tag": null, "extra_fields": {"rawName": "forage", "confidence_score": 0.3606, "domains": ["Hydraulics", "Environment"], "origin": "entity_fishing"}}}, {"start": 404, "end": 426, "mention": null, "origin": "entity_fishing", "annotation": {"wikidata_entity_id": "Q667186", "wikipedia_page_id": 240155, "wikipedia_page_title": null, "wikidata_entity_url": "http://www.wikidata.org/entity/Q667186", "grobid_tag": null, "extra_fields": {"rawName": "forage", "confidence_score": 0.3606, "domains": ["Hydraulics", "Environment"], "origin": "entity_fishing"}}}, {"start": 484, "end": 507, "mention": null, "origin": "entity_fishing", "annotation": {"wikidata_entity_id": "Q2986535", "wikipedia_page_id": 1710743, "wikipedia_page_title": null, "wikidata_entity_url": "http://www.wikidata.org/entity/Q2986535", "grobid_tag": null, "extra_fields": {"rawName": "forage", "confidence_score": 0.3606, "domains": ["Hydraulics", "Environment"], "origin": "entity_fishing"}}}, {"start": 570, "end": 572, "mention": null, "origin": "entity_fishing", "annotation": {"wikidata_entity_id": null, "wikipedia_page_id": null, "wikipedia_page_title": null, "wikidata_entity_url": null, "grobid_tag": "PERSON", "extra_fields": {"rawName": "forage", "confidence_score": 0.3606, "domains": ["Hydraulics", "Environment"], "origin": "entity_fishing"}}}, {"start": 650, "end": 669, "mention": null, "origin": "entity_fishing", "annotation": {"wikidata_entity_id": "Q659309", "wikipedia_page_id": 443449, "wikipedia_page_title": null, "wikidata_entity_url": "http://www.wikidata.org/entity/Q659309", "grobid_tag": null, "extra_fields": {"rawName": "forage", "confidence_score": 0.3606, "domains": ["Hydraulics", "Environment"], "origin": "entity_fishing"}}}, {"start": 762, "end": 785, "mention": null, "origin": "entity_fishing", "annotation": {"wikidata_entity_id": "Q20983805", "wikipedia_page_id": 141228, "wikipedia_page_title": null, "wikidata_entity_url": "http://www.wikidata.org/entity/Q20983805", "grobid_tag": null, "extra_fields": {"rawName": "forage", "confidence_score": 0.3606, "domains": ["Hydraulics", "Environment"], "origin": "entity_fishing"}}}, {"start": 837, "end": 844, "mention": null, "origin": "entity_fishing", "annotation": {"wikidata_entity_id": "Q64186", "wikipedia_page_id": 219572, "wikipedia_page_title": null, "wikidata_entity_url": "http://www.wikidata.org/entity/Q64186", "grobid_tag": null, "extra_fields": {"rawName": "forage", "confidence_score": 0.3606, "domains": ["Hydraulics", "Environment"], "origin": "entity_fishing"}}, "href": "fr/articles/001851", "dhsid": "001851", "wiki": {"item": "http://www.wikidata.org/entity/Q64186", "itemLabel": "Bad Zurzach", "dhsid": "001851", "namefr": "Bad Zurzach", "articlefr": "https://fr.wikipedia.org/wiki/Bad_Zurzach", "namede": "Bad Zurzach", "articlede": "https://de.wikipedia.org/wiki/Bad_Zurzach", "nameit": "Bad Zurzach", "articleit": "https://it.wikipedia.org/wiki/Bad_Zurzach", "nameen": "Bad Zurzach", "articleen": "https://en.wikipedia.org/wiki/Bad_Zurzach", "instanceof": "http://www.wikidata.org/entity/Q902814", "instanceofLabel": "ville frontali\u00e8re", "gndid": "4068142-7", "wikidata_id": "Q64186"}}, {"start": 932, "end": 938, "mention": null, "origin": "entity_fishing", "annotation": {"wikidata_entity_id": "Q14693887", "wikipedia_page_id": 523050, "wikipedia_page_title": null, "wikidata_entity_url": "http://www.wikidata.org/entity/Q14693887", "grobid_tag": null, "extra_fields": {"rawName": "forage", "confidence_score": 0.3606, "domains": ["Hydraulics", "Environment"], "origin": "entity_fishing"}}}]], "wiki_links": [{"item": "http://www.wikidata.org/entity/Q107044169", "itemLabel": "Walter Edelmann", "dhsid": "020339", "namefr": "", "articlefr": "", "namede": "", "articlede": "", "nameit": "", "articleit": "", "nameen": "", "articleen": "", "instanceof": "http://www.wikidata.org/entity/Q5", "instanceofLabel": "\u00eatre humain", "gndid": "1050112008"}], "wikidata_url": "http://www.wikidata.org/entity/Q107044169", "wikipedia_page_title": null, "added_wikidata_wikipedia_to_text_links": true, "_initial": "E", "url": "https://hls-dhs-dss.ch/fr/articles/020339/2004-07-26"}